Workbook

Sheet README
B2: Sasha's Corner — Finance Workbook (v4)
B3: Full recipe system. Change an ingredient price → every menu item cost and P&L number recalculates.
B6: Colour code
B7: Blue text | C7: Numbers YOU type in
B8: Black text | C8: Formulas — calculate automatically
B9: Yellow fill | C9: Key inputs you'll change often
B10: Orange fill | C10: Industry estimate — verify against your invoices
B11: Red fill | C11: Needs your clarification
B13: How data flows
B14: Ingredients tab | C14: Raw material cost per unit. Single source of truth for all prices.
B15: Recipes tab | C15: Every item × size pairing with its ingredient list. Cost = SUM(qty × cost-per-unit) via lookup.
B16: Menu Items tab | C16: Summary of all 175 items — pulls cost price from Recipes.
B17: Daily Sales | C17: Daily totals: Square card / Square cash / own cash. Own cash pulls from Cash Transactions.
B18: Cash Transactions | C18: Log each non-Square cash sale by item. Dropdowns from your menu.
B19: Expenses | C19: Everything the business spends money on.
B20: Monthly P&L | C20: 12-month matrix showing revenue, COGS, opex, profit per month + annual total.
B21: Yearly Summary | C21: YTD totals, trends, best/worst months, card-vs-cash split.
B22: Dashboard | C22: At-a-glance view: this month, YTD, progress to target.
B24: The most important thing to understand
B25: Base prices assume whole milk. | C25: If a customer swaps to oat/almond/coconut/soy they pay the +£0.50 upcharge (tracked via Square as 'Oat milk' or 'Coconut milk' add-on). Your extra cost is ~£0.25 per swap. Net extra profit ≈ £0.25 per alt-milk drink.
B27: Priority actions
B28: A | C28: Verify Ingredients — orange costs are estimates. Replace with invoice prices. Everything else recalculates.
B29: B | C29: Answer the 12 open questions in Sources & Assumptions (the red-flagged items).
B30: C | C30: Start logging Daily Sales + Cash Transactions + Expenses from tomorrow.
B31: D | C31: End of each month: glance at Monthly P&L row for that month. Any margin under 60% → investigate.
B32: E | C32: When you have time, fix the item-name typos in Square (they're documented in Sources & Assumptions).
B35: Data status (last updated 28 Apr 2026)
B36: Daily Sales | C36: Sep 2025 → Apr 2026 imported. Card sales for Sep-Mar are from Mettle Square deposits (date = deposit date, ~1 day after actual sale). April uses actual Square Dashboard data.
B37: Just Eat | C37: Delivery sales (£114.92 over 7 events) recorded in 'Square — cash' column with notes.
B38: Expenses | C38: All Mettle bank outflows imported and categorised. Personal-looking spend tagged 'Director drawings' in notes. Capital expenditure (setup/equipment) tagged similarly in 'Other' category.
B39: Director Account | C39: New tab tracking your £6,850 capital injections IN vs your drawings OUT. Not part of operating P&L.

Sheet Ingredients
B2: Ingredients — Master Price List
B3: Every raw material. Orange = estimate — REPLACE with YOUR invoice prices. All recipes and margins recalculate automatically.
B5: Ingredient | C5: Category | D5: Pack size | E5: Pack unit | F5: Pack cost (£) | G5: Cost per unit | H5: Unit | I5: Supplier / notes
B6: Whole milk | C6: Dairy | D6: 13.62 | E6: L | F6: 9.98 | G6: =IFERROR(F6/D6,0) -> 0.73274596 | H6: L | I6: Real invoice — 3.4L = £2.37
B7: Semi-skimmed milk | C7: Dairy | D7: 3.4 | E7: L | F7: 2.37 | G7: =IFERROR(F7/D7,0) -> 0.69705882 | H7: L | I7: Same as whole — assumed
B8: Oat milk (barista) | C8: Dairy alt | D8: 1 | E8: L | F8: 2.5 | G8: =IFERROR(F8/D8,0) -> 2.5 | H8: L | I8: Real invoice — alt-milk £2.50/L
B9: Almond milk (barista) | C9: Dairy alt | D9: 1 | E9: L | F9: 2.5 | G9: =IFERROR(F9/D9,0) -> 2.5 | H9: L | I9: Real invoice — alt-milk £2.50/L
B10: Soy milk (barista) | C10: Dairy alt | D10: 1 | E10: L | F10: 2.5 | G10: =IFERROR(F10/D10,0) -> 2.5 | H10: L | I10: Real invoice — alt-milk £2.50/L
B11: Coconut milk (barista) | C11: Dairy alt | D11: 1 | E11: L | F11: 2.5 | G11: =IFERROR(F11/D11,0) -> 2.5 | H11: L | I11: Real invoice — alt-milk £2.50/L
B12: Whipping cream | C12: Dairy | D12: 1 | E12: L | F12: 6.8 | G12: =IFERROR(F12/D12,0) -> 6.8 | H12: L | I12: ESTIMATE
B13: Coffee beans (house blend) | C13: Coffee | D13: 6 | E13: kg | F13: 97.5 | G13: =IFERROR(F13/D13,0) -> 16.25 | H13: kg | I13: Real invoice — £95 per 5kg
B14: Coffee beans (decaf) | C14: Coffee | D14: 1 | E14: kg | F14: 24 | G14: =IFERROR(F14/D14,0) -> 24 | H14: kg | I14: ESTIMATE
B15: Vanilla syrup (Monin) | C15: Syrup | D15: 1000 | E15: ml | F15: 5 | G15: =IFERROR(F15/D15,0) -> 0.005 | H15: ml | I15: Real invoice — Monin £9/L
B16: Caramel syrup (Monin) | C16: Syrup | D16: 1000 | E16: ml | F16: 5 | G16: =IFERROR(F16/D16,0) -> 0.005 | H16: ml | I16: Real invoice — Monin £9/L
B17: Salted caramel syrup (Monin) | C17: Syrup | D17: 1000 | E17: ml | F17: 5 | G17: =IFERROR(F17/D17,0) -> 0.005 | H17: ml | I17: Real invoice — Monin £9/L
... B118: Decaf coffee pod | C118: Coffee | D118: 18 | E118: unit | F118: 7.5 | G118: =IFERROR(F118/D118,0) -> 0.41666667 | H118: unit | I118: Real invoice — 18 pods = £7.50 (£0.42/pod). Use 1 pod for S, 2 for M, 3 for L.
B119: Frappe powder | C119: Specialty | D119: 1 | E119: kg | F119: 8.5 | G119: =IFERROR(F119/D119,0) -> 8.5 | H119: For milkshakes (60g per drink)
B120: Orange juice | C120: Specialty | D120: 1 | E120: L | F120: 1.5 | G120: =IFERROR(F120/D120,0) -> 1.5 | H120: Estimate — verify supplier price
G121: =IFERROR(F121/D121,0) -> 0
G122: =IFERROR(F122/D122,0) -> 0
G123: =IFERROR(F123/D123,0) -> 0
G124: =IFERROR(F124/D124,0) -> 0
G125: =IFERROR(F125/D125,0) -> 0
G126: =IFERROR(F126/D126,0) -> 0
G127: =IFERROR(F127/D127,0) -> 0
G128: =IFERROR(F128/D128,0) -> 0
G129: =IFERROR(F129/D129,0) -> 0
G130: =IFERROR(F130/D130,0) -> 0
G131: =IFERROR(F131/D131,0) -> 0
G132: =IFERROR(F132/D132,0) -> 0
... G301: =IFERROR(F301/D301,0) -> 0

Sheet Recipes
B2: Recipes — Ingredient Details per Item/Size
B3: Every item × size with its ingredients. Cost calculates from Ingredients prices via lookup. Add ingredient rows using the blank rows at the end — pick ingredient from dropdown.
B5: RECIPE SUMMARY
B6: Recipe # | C6: Item name | D6: Size | E6: Category | F6: Sell price (£) | G6: Cost price (£) | H6: Gross profit (£) | I6: Margin % | J6: # ingredients | K6: Notes | L6: Markup %
B7: 1 | C7: Banana Milkshake | D7: M | F7: 4.6 | G7: =IFERROR(SUMIFS(H328:H1942,B328:B1942,B7),0) -> 0.93991189 | H7: =F7-G7 -> 3.6600881 | I7: =IFERROR((F7-G7)/F7,0) -> 0.79567133 | J7: 5 | K7: Milkshake | L7: =IFERROR((F7-G7)/G7,0) -> 3.8940757
B8: 2 | C8: Banana Milkshake | D8: S | F8: 4.4 | G8: =IFERROR(SUMIFS(H328:H1942,B328:B1942,B8),0) -> 0.90991189 | H8: =F8-G8 -> 3.4900881 | I8: =IFERROR((F8-G8)/F8,0) -> 0.79320184 | J8: 5 | K8: Milkshake | L8: =IFERROR((F8-G8)/G8,0) -> 3.835633
B9: 3 | C9: Banana and Pecan Muffin | D9: M | F9: 3.2 | G9: =IFERROR(SUMIFS(H328:H1942,B328:B1942,B9),0) -> 1.3 | H9: =F9-G9 -> 1.9 | I9: =IFERROR((F9-G9)/F9,0) -> 0.59375 | J9: 1 | K9: Wholesale cake (CakeSmiths or similar) | L9: =IFERROR((F9-G9)/G9,0) -> 1.4615385
B10: 4 | C10: Berry Breeze Lemonade | D10: M | F10: 0 | G10: =IFERROR(SUMIFS(H328:H1942,B328:B1942,B10),0) -> 0 | H10: =F10-G10 -> 0 | I10: =IFERROR((F10-G10)/F10,0) -> 0 | J10: 4 | K10: Fruit lemonade (approx) | L10: =IFERROR((F10-G10)/G10,0) -> 0
B11: 5 | C11: Berry Breeze Lemonade | D11: S | F11: 0 | G11: =IFERROR(SUMIFS(H328:H1942,B328:B1942,B11),0) -> 0 | H11: =F11-G11 -> 0 | I11: =IFERROR((F11-G11)/F11,0) -> 0 | J11: 4 | K11: Fruit lemonade (approx) | L11: =IFERROR((F11-G11)/G11,0) -> 0
B12: 6 | C12: Berry Tea | D12: One | E12: Teas | F12: 1.9 | G12: =IFERROR(SUMIFS(H328:H1942,B328:B1942,B12),0) -> 0.199875 | H12: =F12-G12 -> 1.700125 | I12: =IFERROR((F12-G12)/F12,0) -> 0.89480263 | J12: 3 | K12: Hot tea | L12: =IFERROR((F12-G12)/G12,0) -> 8.5059412
B13: 7 | C13: Black Americano | D13: M | F13: 3.1 | G13: =IFERROR(SUMIFS(H328:H1942,B328:B1942,B13),0) -> 0.725 | H13: =F13-G13 -> 2.375 | I13: =IFERROR((F13-G13)/F13,0) -> 0.76612903 | J13: 3 | K13: Americano | L13: =IFERROR((F13-G13)/G13,0) -> 3.2758621
B14: 8 | C14: Black Americano | D14: S | F14: 2.8 | G14: =IFERROR(SUMIFS(H328:H1942,B328:B1942,B14),0) -> 0.705 | H14: =F14-G14 -> 2.095 | I14: =IFERROR((F14-G14)/F14,0) -> 0.74821429 | J14: 3 | K14: Americano | L14: =IFERROR((F14-G14)/G14,0) -> 2.9716312
B15: 9 | C15: Black Americano | D15: XL | F15: 3.4 | G15: =IFERROR(SUMIFS(H328:H1942,B328:B1942,B15),0) -> 1.34 | H15: =F15-G15 -> 2.06 | I15: =IFERROR((F15-G15)/F15,0) -> 0.60588235 | J15: 3 | K15: Americano | L15: =IFERROR((F15-G15)/G15,0) -> 1.5373134
B16: 10 | C16: Black Honey | D16: M | F16: 4 | G16: =IFERROR(SUMIFS(H328:H1942,B328:B1942,B16),0) -> 0.367875 | H16: =F16-G16 -> 3.632125 | I16: =IFERROR((F16-G16)/F16,0) -> 0.90803125 | J16: 4 | K16: Unclear — treated as tea-based drink | L16: =IFERROR((F16-G16)/G16,0) -> 9.8732586
B17: 11 | C17: Black Honey | D17: S | F17: 3.8 | G17: =IFERROR(SUMIFS(H328:H1942,B328:B1942,B17),0) -> 0.347875 | H17: =F17-G17 -> 3.452125 | I17: =IFERROR((F17-G17)/F17,0) -> 0.90845395 | J17: 4 | K17: Unclear — treated as tea-based drink | L17: =IFERROR((F17-G17)/G17,0) -> 9.9234639
B18: 12 | C18: Blue Honey Matcha | D18: M | E18: Spring saesonal drinks | F18: 4.2 | G18: =IFERROR(SUMIFS(H328:H1942,B328:B1942,B18),0) -> 0.78213363 | H18: =F18-G18 -> 3.4178664 | I18: =IFERROR((F18-G18)/F18,0) -> 0.81377771 | J18: 5 | K18: Hot matcha (blue = butterfly pea) | L18: =IFERROR((F18-G18)/G18,0) -> 4.3699264
B19: 13 | C19: Blue Honey Matcha | D19: S | E19: Spring saesonal drinks | F19: 4 | G19: =IFERROR(SUMIFS(H328:H1942,B328:B1942,B19),0) -> 0.67420411 | H19: =F19-G19 -> 3.3257959 | I19: =IFERROR((F19-G19)/F19,0) -> 0.83144897 | J19: 5 | K19: Hot matcha (blue = butterfly pea) | L19: =IFERROR((F19-G19)/G19,0) -> 4.9329214
B20: 14 | C20: Blue Honey Matcha | D20: XL | E20: Spring saesonal drinks | F20: 4.6 | G20: =IFERROR(SUMIFS(H328:H1942,B328:B1942,B20),0) -> 0.90006314 | H20: =F20-G20 -> 3.6999369 | I20: =IFERROR((F20-G20)/F20,0) -> 0.8043341 | J20: 5 | K20: Hot matcha (blue = butterfly pea) | L20: =IFERROR((F20-G20)/G20,0) -> 4.1107525
B21: 15 | C21: Blue Lavender Matcha | D21: M | E21: Spring saesonal drinks | F21: 4.2 | G21: =IFERROR(SUMIFS(H328:H1942,B328:B1942,B21),0) -> 0.76413363 | H21: =F21-G21 -> 3.4358664 | I21: =IFERROR((F21-G21)/F21,0) -> 0.81806342 | J21: 5 | K21: Hot matcha (blue = butterfly pea) | L21: =IFERROR((F21-G21)/G21,0) -> 4.4964209
B22: 16 | C22: Blue Lavender Matcha | D22: S | E22: Spring saesonal drinks | F22: 4 | G22: =IFERROR(SUMIFS(H328:H1942,B328:B1942,B22),0) -> 0.65620411 | H22: =F22-G22 -> 3.3437959 | I22: =IFERROR((F22-G22)/F22,0) -> 0.83594897 | J22: 5 | K22: Hot matcha (blue = butterfly pea) | L22: =IFERROR((F22-G22)/G22,0) -> 5.0956643
B23: 17 | C23: Blue Lavender Matcha | D23: XL | E23: Spring saesonal drinks | F23: 4.6 | G23: =IFERROR(SUMIFS(H328:H1942,B328:B1942,B23),0) -> 0.88206314 | H23: =F23-G23 -> 3.7179369 | I23: =IFERROR((F23-G23)/F23,0) -> 0.80824714 | J23: 5 | K23: Hot matcha (blue = butterfly pea) | L23: =IFERROR((F23-G23)/G23,0) -> 4.2150462
B24: 18 | C24: Blue Vanilla Matcha | D24: M | E24: Spring saesonal drinks | F24: 4.2 | G24: =IFERROR(SUMIFS(H328:H1942,B328:B1942,B24),0) -> 0.76413363 | H24: =F24-G24 -> 3.4358664 | I24: =IFERROR((F24-G24)/F24,0) -> 0.81806342 | J24: 5 | K24: Hot matcha (blue = butterfly pea) | L24: =IFERROR((F24-G24)/G24,0) -> 4.4964209
B25: 19 | C25: Blue Vanilla Matcha | D25: S | E25: Spring saesonal drinks | F25: 4 | G25: =IFERROR(SUMIFS(H328:H1942,B328:B1942,B25),0) -> 0.65620411 | H25: =F25-G25 -> 3.3437959 | I25: =IFERROR((F25-G25)/F25,0) -> 0.83594897 | J25: 5 | K25: Hot matcha (blue = butterfly pea) | L25: =IFERROR((F25-G25)/G25,0) -> 5.0956643
B26: 20 | C26: Blue Vanilla Matcha | D26: XL | E26: Spring saesonal drinks | F26: 4.6 | G26: =IFERROR(SUMIFS(H328:H1942,B328:B1942,B26),0) -> 0.88206314 | H26: =F26-G26 -> 3.7179369 | I26: =IFERROR((F26-G26)/F26,0) -> 0.80824714 | J26: 5 | K26: Hot matcha (blue = butterfly pea) | L26: =IFERROR((F26-G26)/G26,0) -> 4.2150462
B27: 21 | C27: Butterfly (lavender) Latte | D27: M | E27: Spring saesonal drinks | F27: 4.1 | G27: =IFERROR(SUMIFS(H328:H1942,B328:B1942,B27),0) -> 1.0948238 | H27: =F27-G27 -> 3.0051762 | I27: =IFERROR((F27-G27)/F27,0) -> 0.73296981 | J27: 5 | K27: Flavoured latte (Lavender syrup (Monin)) | L27: =IFERROR((F27-G27)/G27,0) -> 2.7448949
B28: 22 | C28: Butterfly (lavender) Latte | D28: S | E28: Spring saesonal drinks | F28: 3.9 | G28: =IFERROR(SUMIFS(H328:H1942,B328:B1942,B28),0) -> 0.98689427 | H28: =F28-G28 -> 2.9131057 | I28: =IFERROR((F28-G28)/F28,0) -> 0.74695019 | J28: 5 | K28: Flavoured latte (Lavender syrup (Monin)) | L28: =IFERROR((F28-G28)/G28,0) -> 2.9517911
B29: 23 | C29: Butterfly (lavender) Latte | D29: XL | E29: Spring saesonal drinks | F29: 4.3 | G29: =IFERROR(SUMIFS(H328:H1942,B328:B1942,B29),0) -> 1.7537885 | H29: =F29-G29 -> 2.5462115 | I29: =IFERROR((F29-G29)/F29,0) -> 0.5921422 | J29: 5 | K29: Flavoured latte (Lavender syrup (Monin)) | L29: =IFERROR((F29-G29)/G29,0) -> 1.4518349
B30: 24 | C30: Butterfly Hot Chocolate | D30: M | F30: 4.2 | G30: =IFERROR(SUMIFS(H328:H1942,B328:B1942,B30),0) -> 0.59913363 | H30: =F30-G30 -> 3.6008664 | I30: =IFERROR((F30-G30)/F30,0) -> 0.85734914 | J30: 4 | K30: Hot chocolate | L30: =IFERROR((F30-G30)/G30,0) -> 6.0101223
B31: 25 | C31: Butterfly Hot Chocolate | D31: S | F31: 4 | G31: =IFERROR(SUMIFS(H328:H1942,B328:B1942,B31),0) -> 0.42120411 | H31: =F31-G31 -> 3.5787959 | I31: =IFERROR((F31-G31)/F31,0) -> 0.89469897 | J31: 4 | K31: Hot chocolate | L31: =IFERROR((F31-G31)/G31,0) -> 8.4965835
B32: 26 | C32: Butterfly Hot Chocolate | D32: XL | F32: 4.4 | G32: =IFERROR(SUMIFS(H328:H1942,B328:B1942,B32),0) -> 0.78706314 | H32: =F32-G32 -> 3.6129369 | I32: =IFERROR((F32-G32)/F32,0) -> 0.82112201 | J32: 4 | K32: Hot chocolate | L32: =IFERROR((F32-G32)/G32,0) -> 4.5904028
B33: 27 | C33: Cappuccino | D33: M | F33: 3.5 | G33: =IFERROR(SUMIFS(H328:H1942,B328:B1942,B33),0) -> 0.94482379 | H33: =F33-G33 -> 2.5551762 | I33: =IFERROR((F33-G33)/F33,0) -> 0.73005035 | J33: 4 | K33: Cappuccino | L33: =IFERROR((F33-G33)/G33,0) -> 2.7043945
B34: 28 | C34: Cappuccino | D34: S | F34: 3.2 | G34: =IFERROR(SUMIFS(H328:H1942,B328:B1942,B34),0) -> 0.83689427 | H34: =F34-G34 -> 2.3631057 | I34: =IFERROR((F34-G34)/F34,0) -> 0.73847054 | J34: 4 | K34: Cappuccino | L34: =IFERROR((F34-G34)/G34,0) -> 2.823661
B35: 29 | C35: Cappuccino | D35: XL | F35: 3.8 | G35: =IFERROR(SUMIFS(H328:H1942,B328:B1942,B35),0) -> 1.6037885 | H35: =F35-G35 -> 2.1962115 | I35: =IFERROR((F35-G35)/F35,0) -> 0.57795038 | J35: 4 | K35: Cappuccino | L35: =IFERROR((F35-G35)/G35,0) -> 1.3693897
B36: 30 | C36: Chai Latte | D36: M | F36: 3.7 | G36: =IFERROR(SUMIFS(H328:H1942,B328:B1942,B36),0) -> 0.78784141 | H36: =F36-G36 -> 2.9121586 | I36: =IFERROR((F36-G36)/F36,0) -> 0.78706989 | J36: 4 | K36: Chai latte | L36: =IFERROR((F36-G36)/G36,0) -> 3.6963766
B37: 31 | C37: Chai Latte | D37: S | F37: 3.4 | G37: =IFERROR(SUMIFS(H328:H1942,B328:B1942,B37),0) -> 0.55189427 | H37: =F37-G37 -> 2.8481057 | I37: =IFERROR((F37-G37)/F37,0) -> 0.83767815 | J37: 4 | K37: Chai latte | L37: =IFERROR((F37-G37)/G37,0) -> 5.1606003
B38: 32 | C38: Chai Latte | D38: XL | F38: 4 | G38: =IFERROR(SUMIFS(H328:H1942,B328:B1942,B38),0) -> 1.0337885 | H38: =F38-G38 -> 2.9662115 | I38: =IFERROR((F38-G38)/F38,0) -> 0.74155286 | J38: 4 | K38: Chai latte | L38: =IFERROR((F38-G38)/G38,0) -> 2.8692632
B39: 33 | C39: Chocolate Coffee Milkshake | D39: M | F39: 4.6 | G39: =IFERROR(SUMIFS(H328:H1942,B328:B1942,B39),0) -> 1.2924119 | H39: =F39-G39 -> 3.3075881 | I39: =IFERROR((F39-G39)/F39,0) -> 0.71904089 | J39: 6 | K39: Milkshake | L39: =IFERROR((F39-G39)/G39,0) -> 2.5592368
B40: 34 | C40: Chocolate Coffee Milkshake | D40: S | F40: 4.4 | G40: =IFERROR(SUMIFS(H328:H1942,B328:B1942,B40),0) -> 1.2624119 | H40: =F40-G40 -> 3.1375881 | I40: =IFERROR((F40-G40)/F40,0) -> 0.71308821 | J40: 6 | K40: Milkshake | L40: =IFERROR((F40-G40)/G40,0) -> 2.4853917
B41: 35 | C41: Chocolate Milkshake | D41: M | F41: 4.6 | G41: =IFERROR(SUMIFS(H328:H1942,B328:B1942,B41),0) -> 0.99991189 | H41: =F41-G41 -> 3.6000881 | I41: =IFERROR((F41-G41)/F41,0) -> 0.78262785 | J41: 5 | K41: Milkshake | L41: =IFERROR((F41-G41)/G41,0) -> 3.6004053
B42: 36 | C42: Chocolate Milkshake | D42: S | F42: 4.2 | G42: =IFERROR(SUMIFS(H328:H1942,B328:B1942,B42),0) -> 0.96991189 | H42: =F42-G42 -> 3.2300881 | I42: =IFERROR((F42-G42)/F42,0) -> 0.7690686 | J42: 5 | K42: Milkshake | L42: =IFERROR((F42-G42)/G42,0) -> 3.3302902
B43: 37 | C43: Cinnamon classic | D43: M | F43: 3 | G43: =IFERROR(SUMIFS(H328:H1942,B328:B1942,B43),0) -> 1.74 | H43: =F43-G43 -> 1.26 | I43: =IFERROR((F43-G43)/F43,0) -> 0.42 | J43: 1 | K43: Wholesale cake (CakeSmiths or similar) | L43: =IFERROR((F43-G43)/G43,0) -> 0.72413793
B44: 38 | C44: Cinnamon Bun Hot Chocolate | D44: M | F44: 4.2 | G44: =IFERROR(SUMIFS(H328:H1942,B328:B1942,B44),0) -> 0.59913363 | H44: =F44-G44 -> 3.6008664 | I44: =IFERROR((F44-G44)/F44,0) -> 0.85734914 | J44: 4 | K44: Hot chocolate | L44: =IFERROR((F44-G44)/G44,0) -> 6.0101223
B45: 39 | C45: Cinnamon Bun Hot Chocolate | D45: S | F45: 4 | G45: =IFERROR(SUMIFS(H328:H1942,B328:B1942,B45),0) -> 0.42120411 | H45: =F45-G45 -> 3.5787959 | I45: =IFERROR((F45-G45)/F45,0) -> 0.89469897 | J45: 4 | K45: Hot chocolate | L45: =IFERROR((F45-G45)/G45,0) -> 8.4965835
B46: 40 | C46: Cinnamon Bun Hot Chocolate | D46: XL | F46: 4.6 | G46: =IFERROR(SUMIFS(H328:H1942,B328:B1942,B46),0) -> 0.78706314 | H46: =F46-G46 -> 3.8129369 | I46: =IFERROR((F46-G46)/F46,0) -> 0.82889932 | J46: 4 | K46: Hot chocolate | L46: =IFERROR((F46-G46)/G46,0) -> 4.844512
B47: 41 | C47: Cinnamon Bun Latte | D47: M | F47: 4.1 | G47: =IFERROR(SUMIFS(H328:H1942,B328:B1942,B47),0) -> 0.94482379 | H47: =F47-G47 -> 3.1551762 | I47: =IFERROR((F47-G47)/F47,0) -> 0.76955517 | J47: 4 | K47: Flavoured latte (Cinnamon bun syrup (Monin)) | L47: =IFERROR((F47-G47)/G47,0) -> 3.3394335
B48: 42 | C48: Cinnamon Bun Latte | D48: S | F48: 3.9 | G48: =IFERROR(SUMIFS(H328:H1942,B328:B1942,B48),0) -> 0.83689427 | H48: =F48-G48 -> 3.0631057 | I48: =IFERROR((F48-G48)/F48,0) -> 0.78541172 | J48: 4 | K48: Flavoured latte (Cinnamon bun syrup (Monin)) | L48: =IFERROR((F48-G48)/G48,0) -> 3.6600869
B49: 43 | C49: Cinnamon Bun Latte | D49: XL | F49: 4.5 | G49: =IFERROR(SUMIFS(H328:H1942,B328:B1942,B49),0) -> 1.6037885 | H49: =F49-G49 -> 2.8962115 | I49: =IFERROR((F49-G49)/F49,0) -> 0.64360255 | J49: 4 | K49: Flavoured latte (Cinnamon bun syrup (Monin)) | L49: =IFERROR((F49-G49)/G49,0) -> 1.8058562
B50: 44 | C50: Coffee Milkshake | D50: M | F50: 4.5 | G50: =IFERROR(SUMIFS(H328:H1942,B328:B1942,B50),0) -> 1.0824119 | H50: =F50-G50 -> 3.4175881 | I50: =IFERROR((F50-G50)/F50,0) -> 0.75946402 | J50: 5 | K50: Milkshake | L50: =IFERROR((F50-G50)/G50,0) -> 3.1573823
B51: 45 | C51: Coffee Milkshake | D51: S | F51: 4.1 | G51: =IFERROR(SUMIFS(H328:H1942,B328:B1942,B51),0) -> 1.0524119 | H51: =F51-G51 -> 3.0475881 | I51: =IFERROR((F51-G51)/F51,0) -> 0.74331417 | J51: 5 | K51: Milkshake | L51: =IFERROR((F51-G51)/G51,0) -> 2.8958131
B52: 46 | C52: Cortado | D52: One | F52: 3.1 | G52: =IFERROR(SUMIFS(H328:H1942,B328:B1942,B52),0) -> 0.83689427 | H52: =F52-G52 -> 2.2631057 | I52: =IFERROR((F52-G52)/F52,0) -> 0.73003411 | J52: 4 | K52: Cortado | L52: =IFERROR((F52-G52)/G52,0) -> 2.7041716
B53: 47 | C53: Decaf Tea | D53: One | E53: Teas | F53: 1.9 | G53: =IFERROR(SUMIFS(H328:H1942,B328:B1942,B53),0) -> 0.199875 | H53: =F53-G53 -> 1.700125 | I53: =IFERROR((F53-G53)/F53,0) -> 0.89480263 | J53: 3 | K53: Hot tea | L53: =IFERROR((F53-G53)/G53,0) -> 8.5059412
B54: 48 | C54: Double Espresso | D54: One | F54: 2 | G54: =IFERROR(SUMIFS(H328:H1942,B328:B1942,B54),0) -> 0.705 | H54: =F54-G54 -> 1.295 | I54: =IFERROR((F54-G54)/F54,0) -> 0.6475 | J54: 3 | K54: Double espresso | L54: =IFERROR((F54-G54)/G54,0) -> 1.8368794
B55: 49 | C55: Double Espresso Con Pana | D55: One | F55: 2.4 | G55: =IFERROR(SUMIFS(H328:H1942,B328:B1942,B55),0) -> 0.841 | H55: =F55-G55 -> 1.559 | I55: =IFERROR((F55-G55)/F55,0) -> 0.64958333 | J55: 4 | K55: Double espresso + whipped cream | L55: =IFERROR((F55-G55)/G55,0) -> 1.8537455
B56: 50 | C56: Double Macchiato | D56: One | F56: 2.1 | G56: =IFERROR(SUMIFS(H328:H1942,B328:B1942,B56),0) -> 0.81491189 | H56: =F56-G56 -> 1.2850881 | I56: =IFERROR((F56-G56)/F56,0) -> 0.61194672 | J56: 4 | K56: Double macchiato | L56: =IFERROR((F56-G56)/G56,0) -> 1.5769657
B57: 51 | C57: Earl Grey | D57: One | E57: Teas | F57: 1.9 | G57: =IFERROR(SUMIFS(H328:H1942,B328:B1942,B57),0) -> 0.199875 | H57: =F57-G57 -> 1.700125 | I57: =IFERROR((F57-G57)/F57,0) -> 0.89480263 | J57: 3 | K57: Hot tea | L57: =IFERROR((F57-G57)/G57,0) -> 8.5059412
B58: 52 | C58: Emerald Zest | D58: M | F58: 0 | G58: =IFERROR(SUMIFS(H328:H1942,B328:B1942,B58),0) -> 0 | H58: =F58-G58 -> 0 | I58: =IFERROR((F58-G58)/F58,0) -> 0 | J58: 5 | K58: Composition unclear — VERIFY recipe | L58: =IFERROR((F58-G58)/G58,0) -> 0
B59: 53 | C59: Emerald Zest | D59: S | F59: 0 | G59: =IFERROR(SUMIFS(H328:H1942,B328:B1942,B59),0) -> 0 | H59: =F59-G59 -> 0 | I59: =IFERROR((F59-G59)/F59,0) -> 0 | J59: 5 | K59: Composition unclear — VERIFY recipe | L59: =IFERROR((F59-G59)/G59,0) -> 0
B60: 54 | C60: English Breakfast | D60: One | E60: Teas | F60: 1.9 | G60: =IFERROR(SUMIFS(H328:H1942,B328:B1942,B60),0) -> 0.199875 | H60: =F60-G60 -> 1.700125 | I60: =IFERROR((F60-G60)/F60,0) -> 0.89480263 | J60: 3 | K60: Hot tea | L60: =IFERROR((F60-G60)/G60,0) -> 8.5059412
B61: 55 | C61: Espresso Tonic | D61: M | F61: 3.7 | G61: =IFERROR(SUMIFS(H328:H1942,B328:B1942,B61),0) -> 1.5883333 | H61: =F61-G61 -> 2.1116667 | I61: =IFERROR((F61-G61)/F61,0) -> 0.57072072 | J61: 4 | K61: Espresso + tonic | L61: =IFERROR((F61-G61)/G61,0) -> 1.3294858
B62: 56 | C62: Espresso Tonic | D62: S | F62: 3.5 | G62: =IFERROR(SUMIFS(H328:H1942,B328:B1942,B62),0) -> 1.5583333 | H62: =F62-G62 -> 1.9416667 | I62: =IFERROR((F62-G62)/F62,0) -> 0.5547619 | J62: 4 | K62: Espresso + tonic | L62: =IFERROR((F62-G62)/G62,0) -> 1.2459893
B63: 57 | C63: Flat White | D63: One | F63: 3.25 | G63: =IFERROR(SUMIFS(H328:H1942,B328:B1942,B63),0) -> 0.83689427 | H63: =F63-G63 -> 2.4131057 | I63: =IFERROR((F63-G63)/F63,0) -> 0.74249407 | J63: 4 | K63: Flat white | L63: =IFERROR((F63-G63)/G63,0) -> 2.8834057
B64: 58 | C64: Forest Fruits Tea | D64: One | F64: 2 | G64: =IFERROR(SUMIFS(H328:H1942,B328:B1942,B64),0) -> 0.199875 | H64: =F64-G64 -> 1.800125 | I64: =IFERROR((F64-G64)/F64,0) -> 0.9000625 | J64: 3 | K64: Hot tea | L64: =IFERROR((F64-G64)/G64,0) -> 9.0062539
B65: 59 | C65: Ginger and Lemongrass Tea | D65: One | F65: 2 | G65: =IFERROR(SUMIFS(H328:H1942,B328:B1942,B65),0) -> 0.199875 | H65: =F65-G65 -> 1.800125 | I65: =IFERROR((F65-G65)/F65,0) -> 0.9000625 | J65: 3 | K65: Hot tea | L65: =IFERROR((F65-G65)/G65,0) -> 9.0062539
B66: 60 | C66: Green | D66: One | E66: Teas | F66: 1.9 | G66: =IFERROR(SUMIFS(H328:H1942,B328:B1942,B66),0) -> 0.199875 | H66: =F66-G66 -> 1.700125 | I66: =IFERROR((F66-G66)/F66,0) -> 0.89480263 | J66: 3 | K66: Hot tea | L66: =IFERROR((F66-G66)/G66,0) -> 8.5059412
B67: 61 | C67: Green Apple Bubble Tea | D67: M | F67: 4.8 | G67: =IFERROR(SUMIFS(H328:H1942,B328:B1942,B67),0) -> 0.58529919 | H67: =F67-G67 -> 4.2147008 | I67: =IFERROR((F67-G67)/F67,0) -> 0.87806267 | J67: 5 | K67: Bubble tea | L67: =IFERROR((F67-G67)/G67,0) -> 7.2009339
B68: 62 | C68: Green Apple Bubble Tea | D68: S | F68: 4.4 | G68: =IFERROR(SUMIFS(H328:H1942,B328:B1942,B68),0) -> 0.55529919 | H68: =F68-G68 -> 3.8447008 | I68: =IFERROR((F68-G68)/F68,0) -> 0.87379564 | J68: 5 | K68: Bubble tea | L68: =IFERROR((F68-G68)/G68,0) -> 6.9236564
B69: 63 | C69: Honey Bubble Tea | D69: M | F69: 4.8 | G69: =IFERROR(SUMIFS(H328:H1942,B328:B1942,B69),0) -> 0.77129919 | H69: =F69-G69 -> 4.0287008 | I69: =IFERROR((F69-G69)/F69,0) -> 0.83931267 | J69: 5 | K69: Bubble tea | L69: =IFERROR((F69-G69)/G69,0) -> 5.2232659
B70: 64 | C70: Honey Bubble Tea | D70: S | F70: 4.4 | G70: =IFERROR(SUMIFS(H328:H1942,B328:B1942,B70),0) -> 0.74129919 | H70: =F70-G70 -> 3.6587008 | I70: =IFERROR((F70-G70)/F70,0) -> 0.83152291 | J70: 5 | K70: Bubble tea | L70: =IFERROR((F70-G70)/G70,0) -> 4.9355252
B71: 65 | C71: Honey Vanilla Latte | D71: M | E71: Spring saesonal drinks | F71: 4.1 | G71: =IFERROR(SUMIFS(H328:H1942,B328:B1942,B71),0) -> 1.1878238 | H71: =F71-G71 -> 2.9121762 | I71: =IFERROR((F71-G71)/F71,0) -> 0.71028688 | J71: 6 | K71: Flavoured latte (Vanilla syrup (Monin)) | L71: =IFERROR((F71-G71)/G71,0) -> 2.4516904
B72: 66 | C72: Honey Vanilla Latte | D72: S | E72: Spring saesonal drinks | F72: 3.9 | G72: =IFERROR(SUMIFS(H328:H1942,B328:B1942,B72),0) -> 1.0798943 | H72: =F72-G72 -> 2.8201057 | I72: =IFERROR((F72-G72)/F72,0) -> 0.72310403 | J72: 6 | K72: Flavoured latte (Vanilla syrup (Monin)) | L72: =IFERROR((F72-G72)/G72,0) -> 2.6114647
B73: 67 | C73: Honey Vanilla Latte | D73: XL | E73: Spring saesonal drinks | F73: 4.3 | G73: =IFERROR(SUMIFS(H328:H1942,B328:B1942,B73),0) -> 1.8467885 | H73: =F73-G73 -> 2.4532115 | I73: =IFERROR((F73-G73)/F73,0) -> 0.57051429 | J73: 6 | K73: Flavoured latte (Vanilla syrup (Monin)) | L73: =IFERROR((F73-G73)/G73,0) -> 1.3283662
B74: 68 | C74: Hot Chocolate | D74: M | F74: 3.7 | G74: =IFERROR(SUMIFS(H328:H1942,B328:B1942,B74),0) -> 0.59913363 | H74: =F74-G74 -> 3.1008664 | I74: =IFERROR((F74-G74)/F74,0) -> 0.83807199 | J74: 4 | K74: Hot chocolate | L74: =IFERROR((F74-G74)/G74,0) -> 5.1755839
B75: 69 | C75: Hot Chocolate | D75: S | F75: 3.4 | G75: =IFERROR(SUMIFS(H328:H1942,B328:B1942,B75),0) -> 0.42120411 | H75: =F75-G75 -> 2.9787959 | I75: =IFERROR((F75-G75)/F75,0) -> 0.87611644 | J75: 4 | K75: Hot chocolate | L75: =IFERROR((F75-G75)/G75,0) -> 7.0720959
B76: 70 | C76: Hot Chocolate | D76: XL | F76: 4 | G76: =IFERROR(SUMIFS(H328:H1942,B328:B1942,B76),0) -> 0.78706314 | H76: =F76-G76 -> 3.2129369 | I76: =IFERROR((F76-G76)/F76,0) -> 0.80323421 | J76: 4 | K76: Hot chocolate | L76: =IFERROR((F76-G76)/G76,0) -> 4.0821844
B77: 71 | C77: Hot Lavender Matcha | D77: M | F77: 3.9 | G77: =IFERROR(SUMIFS(H328:H1942,B328:B1942,B77),0) -> 1.0406234 | H77: =F77-G77 -> 2.8593766 | I77: =IFERROR((F77-G77)/F77,0) -> 0.73317348 | J77: 5 | K77: Hot matcha | L77: =IFERROR((F77-G77)/G77,0) -> 2.7477535
B78: 72 | C78: Hot Lavender Matcha | D78: S | F78: 3.6 | G78: =IFERROR(SUMIFS(H328:H1942,B328:B1942,B78),0) -> 0.94734882 | H78: =F78-G78 -> 2.6526512 | I78: =IFERROR((F78-G78)/F78,0) -> 0.73684755 | J78: 5 | K78: Hot matcha | L78: =IFERROR((F78-G78)/G78,0) -> 2.8000786
B79: 73 | C79: Hot Lavender Matcha | D79: XL | F79: 4.2 | G79: =IFERROR(SUMIFS(H328:H1942,B328:B1942,B79),0) -> 1.143898 | H79: =F79-G79 -> 3.056102 | I79: =IFERROR((F79-G79)/F79,0) -> 0.72764333 | J79: 5 | K79: Hot matcha | L79: =IFERROR((F79-G79)/G79,0) -> 2.671656
B80: 74 | C80: Hot Matcha | D80: M | F80: 3.7 | G80: =IFERROR(SUMIFS(H328:H1942,B328:B1942,B80),0) -> 0.89062341 | H80: =F80-G80 -> 2.8093766 | I80: =IFERROR((F80-G80)/F80,0) -> 0.75929097 | J80: 4 | K80: Hot matcha | L80: =IFERROR((F80-G80)/G80,0) -> 3.1543934
B81: 75 | C81: Hot Matcha | D81: S | F81: 3.4 | G81: =IFERROR(SUMIFS(H328:H1942,B328:B1942,B81),0) -> 0.79734882 | H81: =F81-G81 -> 2.6026512 | I81: =IFERROR((F81-G81)/F81,0) -> 0.76548564 | J81: 4 | K81: Hot matcha | L81: =IFERROR((F81-G81)/G81,0) -> 3.2641312
B82: 76 | C82: Hot Matcha | D82: XL | F82: 3.9 | G82: =IFERROR(SUMIFS(H328:H1942,B328:B1942,B82),0) -> 0.99389801 | H82: =F82-G82 -> 2.906102 | I82: =IFERROR((F82-G82)/F82,0) -> 0.74515436 | J82: 4 | K82: Hot matcha | L82: =IFERROR((F82-G82)/G82,0) -> 2.9239439
B83: 77 | C83: Hot Rose Matcha | D83: M | F83: 3.9 | G83: =IFERROR(SUMIFS(H328:H1942,B328:B1942,B83),0) -> 1.0406234 | H83: =F83-G83 -> 2.8593766 | I83: =IFERROR((F83-G83)/F83,0) -> 0.73317348 | J83: 5 | K83: Hot matcha | L83: =IFERROR((F83-G83)/G83,0) -> 2.7477535
B84: 78 | C84: Hot Rose Matcha | D84: S | F84: 3.6 | G84: =IFERROR(SUMIFS(H328:H1942,B328:B1942,B84),0) -> 0.94734882 | H84: =F84-G84 -> 2.6526512 | I84: =IFERROR((F84-G84)/F84,0) -> 0.73684755 | J84: 5 | K84: Hot matcha | L84: =IFERROR((F84-G84)/G84,0) -> 2.8000786
B85: 79 | C85: Hot Rose Matcha | D85: XL | F85: 4.2 | G85: =IFERROR(SUMIFS(H328:H1942,B328:B1942,B85),0) -> 1.143898 | H85: =F85-G85 -> 3.056102 | I85: =IFERROR((F85-G85)/F85,0) -> 0.72764333 | J85: 5 | K85: Hot matcha | L85: =IFERROR((F85-G85)/G85,0) -> 2.671656
B86: 80 | C86: Hot Strawberry Matcha | D86: M | F86: 3.9 | G86: =IFERROR(SUMIFS(H328:H1942,B328:B1942,B86),0) -> 1.0406234 | H86: =F86-G86 -> 2.8593766 | I86: =IFERROR((F86-G86)/F86,0) -> 0.73317348 | J86: 5 | K86: Hot matcha | L86: =IFERROR((F86-G86)/G86,0) -> 2.7477535
B87: 81 | C87: Hot Strawberry Matcha | D87: S | F87: 3.6 | G87: =IFERROR(SUMIFS(H328:H1942,B328:B1942,B87),0) -> 0.94734882 | H87: =F87-G87 -> 2.6526512 | I87: =IFERROR((F87-G87)/F87,0) -> 0.73684755 | J87: 5 | K87: Hot matcha | L87: =IFERROR((F87-G87)/G87,0) -> 2.8000786
B88: 82 | C88: Hot Strawberry Matcha | D88: XL | F88: 4.2 | G88: =IFERROR(SUMIFS(H328:H1942,B328:B1942,B88),0) -> 1.143898 | H88: =F88-G88 -> 3.056102 | I88: =IFERROR((F88-G88)/F88,0) -> 0.72764333 | J88: 5 | K88: Hot matcha | L88: =IFERROR((F88-G88)/G88,0) -> 2.671656
B89: 83 | C89: Hot Vanilla Matcha | D89: M | F89: 3.9 | G89: =IFERROR(SUMIFS(H328:H1942,B328:B1942,B89),0) -> 1.0406234 | H89: =F89-G89 -> 2.8593766 | I89: =IFERROR((F89-G89)/F89,0) -> 0.73317348 | J89: 5 | K89: Hot matcha | L89: =IFERROR((F89-G89)/G89,0) -> 2.7477535
B90: 84 | C90: Hot Vanilla Matcha | D90: S | F90: 3.6 | G90: =IFERROR(SUMIFS(H328:H1942,B328:B1942,B90),0) -> 0.94734882 | H90: =F90-G90 -> 2.6526512 | I90: =IFERROR((F90-G90)/F90,0) -> 0.73684755 | J90: 5 | K90: Hot matcha | L90: =IFERROR((F90-G90)/G90,0) -> 2.8000786
B91: 85 | C91: Hot Vanilla Matcha | D91: XL | F91: 4.2 | G91: =IFERROR(SUMIFS(H328:H1942,B328:B1942,B91),0) -> 1.143898 | H91: =F91-G91 -> 3.056102 | I91: =IFERROR((F91-G91)/F91,0) -> 0.72764333 | J91: 5 | K91: Hot matcha | L91: =IFERROR((F91-G91)/G91,0) -> 2.671656
B92: 86 | C92: Hot White Choc Matcha | D92: M | F92: 3.9 | G92: =IFERROR(SUMIFS(H328:H1942,B328:B1942,B92),0) -> 0.89062341 | H92: =F92-G92 -> 3.0093766 | I92: =IFERROR((F92-G92)/F92,0) -> 0.77163502 | J92: 4 | K92: Hot matcha | L92: =IFERROR((F92-G92)/G92,0) -> 3.3789552
B93: 87 | C93: Hot White Choc Matcha | D93: S | F93: 3.6 | G93: =IFERROR(SUMIFS(H328:H1942,B328:B1942,B93),0) -> 0.79734882 | H93: =F93-G93 -> 2.8026512 | I93: =IFERROR((F93-G93)/F93,0) -> 0.77851422 | J93: 4 | K93: Hot matcha | L93: =IFERROR((F93-G93)/G93,0) -> 3.5149625
B94: 88 | C94: Hot White Choc Matcha | D94: XL | F94: 4.2 | G94: =IFERROR(SUMIFS(H328:H1942,B328:B1942,B94),0) -> 0.99389801 | H94: =F94-G94 -> 3.206102 | I94: =IFERROR((F94-G94)/F94,0) -> 0.76335762 | J94: 4 | K94: Hot matcha | L94: =IFERROR((F94-G94)/G94,0) -> 3.2257857
B95: 89 | C95: Iced Butterfly Latte | D95: M | F95: 4.1 | G95: =IFERROR(SUMIFS(H328:H1942,B328:B1942,B95),0) -> 0.90154919 | H95: =F95-G95 -> 3.1984508 | I95: =IFERROR((F95-G95)/F95,0) -> 0.78010995 | J95: 4 | K95: Iced latte | L95: =IFERROR((F95-G95)/G95,0) -> 3.5477274
B96: 90 | C96: Iced Butterfly Latte | D96: S | F96: 3.9 | G96: =IFERROR(SUMIFS(H328:H1942,B328:B1942,B96),0) -> 0.83491189 | H96: =F96-G96 -> 3.0650881 | I96: =IFERROR((F96-G96)/F96,0) -> 0.78592003 | J96: 4 | K96: Iced latte | L96: =IFERROR((F96-G96)/G96,0) -> 3.6711516
B97: 91 | C97: Iced Cinnamon Bun Latte | D97: M | F97: 4.1 | G97: =IFERROR(SUMIFS(H328:H1942,B328:B1942,B97),0) -> 0.90154919 | H97: =F97-G97 -> 3.1984508 | I97: =IFERROR((F97-G97)/F97,0) -> 0.78010995 | J97: 4 | K97: Iced latte | L97: =IFERROR((F97-G97)/G97,0) -> 3.5477274
B98: 92 | C98: Iced Cinnamon Bun Latte | D98: S | F98: 3.9 | G98: =IFERROR(SUMIFS(H328:H1942,B328:B1942,B98),0) -> 0.83491189 | H98: =F98-G98 -> 3.0650881 | I98: =IFERROR((F98-G98)/F98,0) -> 0.78592003 | J98: 4 | K98: Iced latte | L98: =IFERROR((F98-G98)/G98,0) -> 3.6711516
B99: 93 | C99: Iced Citrus Blue Matcha | D99: M | E99: Spring saesonal drinks | F99: 4.8 | G99: =IFERROR(SUMIFS(H328:H1942,B328:B1942,B99),0) -> 0.72085903 | H99: =F99-G99 -> 4.079141 | I99: =IFERROR((F99-G99)/F99,0) -> 0.84982104 | J99: 5 | K99: Iced matcha (blue = butterfly pea) | L99: =IFERROR((F99-G99)/G99,0) -> 5.6587222
B100: 94 | C100: Iced Citrus Blue Matcha | D100: S | E100: Spring saesonal drinks | F100: 4.6 | G100: =IFERROR(SUMIFS(H328:H1942,B328:B1942,B100),0) -> 0.64689427 | H100: =F100-G100 -> 3.9531057 | I100: =IFERROR((F100-G100)/F100,0) -> 0.85937081 | J100: 5 | K100: Iced matcha (blue = butterfly pea) | L100: =IFERROR((F100-G100)/G100,0) -> 6.1108992
B101: 95 | C101: Iced Coconut Water Blue Matcha | D101: M | E101: Spring saesonal drinks | F101: 4.8 | G101: =IFERROR(SUMIFS(H328:H1942,B328:B1942,B101),0) -> 0.72085903 | H101: =F101-G101 -> 4.079141 | I101: =IFERROR((F101-G101)/F101,0) -> 0.84982104 | J101: 5 | K101: Iced matcha (blue = butterfly pea) | L101: =IFERROR((F101-G101)/G101,0) -> 5.6587222
B102: 96 | C102: Iced Coconut Water Blue Matcha | D102: S | E102: Spring saesonal drinks | F102: 4.6 | G102: =IFERROR(SUMIFS(H328:H1942,B328:B1942,B102),0) -> 0.64689427 | H102: =F102-G102 -> 3.9531057 | I102: =IFERROR((F102-G102)/F102,0) -> 0.85937081 | J102: 5 | K102: Iced matcha (blue = butterfly pea) | L102: =IFERROR((F102-G102)/G102,0) -> 6.1108992
...

Sheet Menu Items
B2: Menu Items — 175 Items (pulls from Recipes)
B3: Summary view. Cost prices pulled from the Recipes tab — don't edit cost here, edit the recipe.
B5: # | C5: Item name | D5: Size | E5: Category | F5: Sell price (£) | G5: Cost price (£) | H5: Margin % | I5: Square category
B6: 1 | C6: 'card' (£3.00) | D6: M | E6: Other | F6: 3 | G6: =IFERROR(VLOOKUP(279,Recipes!$B$7:$G$323,6,FALSE()),0) -> 0 | H6: =IFERROR((F6-G6)/F6,0) -> 1
B7: 2 | C7: Afternoon Deal | D7: M | E7: Meal deal | F7: 5 | G7: =IFERROR(VLOOKUP(270,Recipes!$B$7:$G$323,6,FALSE()),0) -> 0 | H7: =IFERROR((F7-G7)/F7,0) -> 1
B8: 3 | C8: Apple Juice | D8: M | E8: Bottled / pre-packed | F8: 1.6 | G8: =IFERROR(VLOOKUP(271,Recipes!$B$7:$G$323,6,FALSE()),0) -> 0 | H8: =IFERROR((F8-G8)/F8,0) -> 1
B9: 4 | C9: BKK Kyiv cake | D9: M | E9: Cake / sweet | F9: 20 | G9: =IFERROR(VLOOKUP(274,Recipes!$B$7:$G$323,6,FALSE()),0) -> 0 | H9: =IFERROR((F9-G9)/F9,0) -> 1
B10: 5 | C10: Babyccino | D10: M | E10: Other | F10: 0.5 | G10: =IFERROR(VLOOKUP(272,Recipes!$B$7:$G$323,6,FALSE()),0) -> 0 | H10: =IFERROR((F10-G10)/F10,0) -> 1
B11: 6 | C11: Banana Milkshake | D11: S | E11: Milkshake | F11: 4.4 | G11: =IFERROR(VLOOKUP(2,Recipes!$B$7:$G$323,6,FALSE()),0) -> 0.90991189 | H11: =IFERROR((F11-G11)/F11,0) -> 0.79320184
B12: 7 | C12: Banana Milkshake | D12: M | E12: Milkshake | F12: 4.6 | G12: =IFERROR(VLOOKUP(1,Recipes!$B$7:$G$323,6,FALSE()),0) -> 0.93991189 | H12: =IFERROR((F12-G12)/F12,0) -> 0.79567133
B13: 8 | C13: Banana and Pecan Muffin | D13: M | E13: Cake / sweet | F13: 3.2 | G13: =IFERROR(VLOOKUP(3,Recipes!$B$7:$G$323,6,FALSE()),0) -> 1.3 | H13: =IFERROR((F13-G13)/F13,0) -> 0.59375
B14: 9 | C14: Berry Breeze Lemonade | D14: S | E14: DISCONTINUED (May 2026) | F14: 0 | G14: =IFERROR(VLOOKUP(5,Recipes!$B$7:$G$323,6,FALSE()),0) -> 0 | H14: =IFERROR((F14-G14)/F14,0) -> 0
B15: 10 | C15: Berry Breeze Lemonade | D15: M | E15: DISCONTINUED (May 2026) | F15: 0 | G15: =IFERROR(VLOOKUP(4,Recipes!$B$7:$G$323,6,FALSE()),0) -> 0 | H15: =IFERROR((F15-G15)/F15,0) -> 0
B16: 11 | C16: Berry Tea | D16: One | E16: Tea | F16: 1.9 | G16: =IFERROR(VLOOKUP(6,Recipes!$B$7:$G$323,6,FALSE()),0) -> 0.199875 | H16: =IFERROR((F16-G16)/F16,0) -> 0.89480263 | I16: Teas
B17: 12 | C17: Billionaire's shortbread | D17: M | E17: Cake / sweet | F17: 3.6 | G17: =IFERROR(VLOOKUP(273,Recipes!$B$7:$G$323,6,FALSE()),0) -> 1.21 | H17: =IFERROR((F17-G17)/F17,0) -> 0.66388889
B18: 13 | C18: Black Americano | D18: S | E18: Americano | F18: 2.8 | G18: =IFERROR(VLOOKUP(8,Recipes!$B$7:$G$323,6,FALSE()),0) -> 0.705 | H18: =IFERROR((F18-G18)/F18,0) -> 0.74821429
B19: 14 | C19: Black Americano | D19: M | E19: Americano | F19: 3.1 | G19: =IFERROR(VLOOKUP(7,Recipes!$B$7:$G$323,6,FALSE()),0) -> 0.725 | H19: =IFERROR((F19-G19)/F19,0) -> 0.76612903
B20: 15 | C20: Black Americano | D20: XL | E20: Americano | F20: 3.4 | G20: =IFERROR(VLOOKUP(9,Recipes!$B$7:$G$323,6,FALSE()),0) -> 1.34 | H20: =IFERROR((F20-G20)/F20,0) -> 0.60588235
B21: 16 | C21: Black Honey | D21: S | E21: Tea | F21: 3.8 | G21: =IFERROR(VLOOKUP(11,Recipes!$B$7:$G$323,6,FALSE()),0) -> 0.347875 | H21: =IFERROR((F21-G21)/F21,0) -> 0.90845395
B22: 17 | C22: Black Honey | D22: M | E22: Tea | F22: 4 | G22: =IFERROR(VLOOKUP(10,Recipes!$B$7:$G$323,6,FALSE()),0) -> 0.367875 | H22: =IFERROR((F22-G22)/F22,0) -> 0.90803125
B23: 18 | C23: Blue Honey Matcha | D23: S | E23: Matcha | F23: 4 | G23: =IFERROR(VLOOKUP(13,Recipes!$B$7:$G$323,6,FALSE()),0) -> 0.67420411 | H23: =IFERROR((F23-G23)/F23,0) -> 0.83144897 | I23: Spring saesonal drinks
B24: 19 | C24: Blue Honey Matcha | D24: M | E24: Matcha | F24: 4.2 | G24: =IFERROR(VLOOKUP(12,Recipes!$B$7:$G$323,6,FALSE()),0) -> 0.78213363 | H24: =IFERROR((F24-G24)/F24,0) -> 0.81377771 | I24: Spring saesonal drinks
B25: 20 | C25: Blue Honey Matcha | D25: XL | E25: Matcha | F25: 4.6 | G25: =IFERROR(VLOOKUP(14,Recipes!$B$7:$G$323,6,FALSE()),0) -> 0.90006314 | H25: =IFERROR((F25-G25)/F25,0) -> 0.8043341 | I25: Spring saesonal drinks
B26: 21 | C26: Blue Lavender Matcha | D26: S | E26: Matcha | F26: 4 | G26: =IFERROR(VLOOKUP(16,Recipes!$B$7:$G$323,6,FALSE()),0) -> 0.65620411 | H26: =IFERROR((F26-G26)/F26,0) -> 0.83594897 | I26: Spring saesonal drinks
B27: 22 | C27: Blue Lavender Matcha | D27: M | E27: Matcha | F27: 4.2 | G27: =IFERROR(VLOOKUP(15,Recipes!$B$7:$G$323,6,FALSE()),0) -> 0.76413363 | H27: =IFERROR((F27-G27)/F27,0) -> 0.81806342 | I27: Spring saesonal drinks
B28: 23 | C28: Blue Lavender Matcha | D28: XL | E28: Matcha | F28: 4.6 | G28: =IFERROR(VLOOKUP(17,Recipes!$B$7:$G$323,6,FALSE()),0) -> 0.88206314 | H28: =IFERROR((F28-G28)/F28,0) -> 0.80824714 | I28: Spring saesonal drinks
B29: 24 | C29: Blue Vanilla Matcha | D29: S | E29: Matcha | F29: 4 | G29: =IFERROR(VLOOKUP(19,Recipes!$B$7:$G$323,6,FALSE()),0) -> 0.65620411 | H29: =IFERROR((F29-G29)/F29,0) -> 0.83594897 | I29: Spring saesonal drinks
B30: 25 | C30: Blue Vanilla Matcha | D30: M | E30: Matcha | F30: 4.2 | G30: =IFERROR(VLOOKUP(18,Recipes!$B$7:$G$323,6,FALSE()),0) -> 0.76413363 | H30: =IFERROR((F30-G30)/F30,0) -> 0.81806342 | I30: Spring saesonal drinks
B31: 26 | C31: Blue Vanilla Matcha | D31: XL | E31: Matcha | F31: 4.6 | G31: =IFERROR(VLOOKUP(20,Recipes!$B$7:$G$323,6,FALSE()),0) -> 0.88206314 | H31: =IFERROR((F31-G31)/F31,0) -> 0.80824714 | I31: Spring saesonal drinks
B32: 27 | C32: Blueberry Muffin | D32: M | E32: Cake / sweet | F32: 3.2 | G32: =IFERROR(VLOOKUP(275,Recipes!$B$7:$G$323,6,FALSE()),0) -> 1.76 | H32: =IFERROR((F32-G32)/F32,0) -> 0.45
B33: 28 | C33: Brownie Bar | D33: M | E33: Cake / sweet | F33: 2.05 | G33: =IFERROR(VLOOKUP(276,Recipes!$B$7:$G$323,6,FALSE()),0) -> 1.09 | H33: =IFERROR((F33-G33)/F33,0) -> 0.46829268
B34: 29 | C34: Butterfly (lavender) Latte | D34: S | E34: Latte / flavoured latte | F34: 3.9 | G34: =IFERROR(VLOOKUP(22,Recipes!$B$7:$G$323,6,FALSE()),0) -> 0.98689427 | H34: =IFERROR((F34-G34)/F34,0) -> 0.74695019 | I34: Spring saesonal drinks
B35: 30 | C35: Butterfly (lavender) Latte | D35: M | E35: Latte / flavoured latte | F35: 4.1 | G35: =IFERROR(VLOOKUP(21,Recipes!$B$7:$G$323,6,FALSE()),0) -> 1.0948238 | H35: =IFERROR((F35-G35)/F35,0) -> 0.73296981 | I35: Spring saesonal drinks
B36: 31 | C36: Butterfly (lavender) Latte | D36: XL | E36: Latte / flavoured latte | F36: 4.3 | G36: =IFERROR(VLOOKUP(23,Recipes!$B$7:$G$323,6,FALSE()),0) -> 1.7537885 | H36: =IFERROR((F36-G36)/F36,0) -> 0.5921422 | I36: Spring saesonal drinks
B37: 32 | C37: Butterfly Hot Chocolate | D37: S | E37: Hot chocolate | F37: 4 | G37: =IFERROR(VLOOKUP(25,Recipes!$B$7:$G$323,6,FALSE()),0) -> 0.42120411 | H37: =IFERROR((F37-G37)/F37,0) -> 0.89469897
B38: 33 | C38: Butterfly Hot Chocolate | D38: M | E38: Hot chocolate | F38: 4.2 | G38: =IFERROR(VLOOKUP(24,Recipes!$B$7:$G$323,6,FALSE()),0) -> 0.59913363 | H38: =IFERROR((F38-G38)/F38,0) -> 0.85734914
B39: 34 | C39: Butterfly Hot Chocolate | D39: XL | E39: Hot chocolate | F39: 4.4 | G39: =IFERROR(VLOOKUP(26,Recipes!$B$7:$G$323,6,FALSE()),0) -> 0.78706314 | H39: =IFERROR((F39-G39)/F39,0) -> 0.82112201
B40: 35 | C40: Cappuccino | D40: S | E40: Cappuccino | F40: 3.2 | G40: =IFERROR(VLOOKUP(28,Recipes!$B$7:$G$323,6,FALSE()),0) -> 0.83689427 | H40: =IFERROR((F40-G40)/F40,0) -> 0.73847054
B41: 36 | C41: Cappuccino | D41: M | E41: Cappuccino | F41: 3.5 | G41: =IFERROR(VLOOKUP(27,Recipes!$B$7:$G$323,6,FALSE()),0) -> 0.94482379 | H41: =IFERROR((F41-G41)/F41,0) -> 0.73005035
B42: 37 | C42: Cappuccino | D42: XL | E42: Cappuccino | F42: 3.8 | G42: =IFERROR(VLOOKUP(29,Recipes!$B$7:$G$323,6,FALSE()),0) -> 1.6037885 | H42: =IFERROR((F42-G42)/F42,0) -> 0.57795038
B43: 38 | C43: Capri-Sun | D43: M | E43: Bottled / pre-packed | F43: 1.6 | G43: =IFERROR(VLOOKUP(277,Recipes!$B$7:$G$323,6,FALSE()),0) -> 0 | H43: =IFERROR((F43-G43)/F43,0) -> 1
B44: 39 | C44: Caramel syrup (add-on) | D44: M | E44: Add-on / modifier | F44: 0.4 | G44: =IFERROR(VLOOKUP(278,Recipes!$B$7:$G$323,6,FALSE()),0) -> 0.15 | H44: =IFERROR((F44-G44)/F44,0) -> 0.625
B45: 40 | C45: Chai Latte | D45: S | E45: Latte / flavoured latte | F45: 3.4 | G45: =IFERROR(VLOOKUP(31,Recipes!$B$7:$G$323,6,FALSE()),0) -> 0.55189427 | H45: =IFERROR((F45-G45)/F45,0) -> 0.83767815
B46: 41 | C46: Chai Latte | D46: M | E46: Latte / flavoured latte | F46: 3.7 | G46: =IFERROR(VLOOKUP(30,Recipes!$B$7:$G$323,6,FALSE()),0) -> 0.78784141 | H46: =IFERROR((F46-G46)/F46,0) -> 0.78706989
B47: 42 | C47: Chai Latte | D47: XL | E47: Latte / flavoured latte | F47: 4 | G47: =IFERROR(VLOOKUP(32,Recipes!$B$7:$G$323,6,FALSE()),0) -> 1.0337885 | H47: =IFERROR((F47-G47)/F47,0) -> 0.74155286
B48: 43 | C48: Chocolate Coffee Milkshake | D48: S | E48: Milkshake | F48: 4.4 | G48: =IFERROR(VLOOKUP(34,Recipes!$B$7:$G$323,6,FALSE()),0) -> 1.2624119 | H48: =IFERROR((F48-G48)/F48,0) -> 0.71308821
B49: 44 | C49: Chocolate Coffee Milkshake | D49: M | E49: Milkshake | F49: 4.6 | G49: =IFERROR(VLOOKUP(33,Recipes!$B$7:$G$323,6,FALSE()),0) -> 1.2924119 | H49: =IFERROR((F49-G49)/F49,0) -> 0.71904089
B50: 45 | C50: Chocolate Milkshake | D50: S | E50: Milkshake | F50: 4.2 | G50: =IFERROR(VLOOKUP(36,Recipes!$B$7:$G$323,6,FALSE()),0) -> 0.96991189 | H50: =IFERROR((F50-G50)/F50,0) -> 0.7690686
B51: 46 | C51: Chocolate Milkshake | D51: M | E51: Milkshake | F51: 4.6 | G51: =IFERROR(VLOOKUP(35,Recipes!$B$7:$G$323,6,FALSE()),0) -> 0.99991189 | H51: =IFERROR((F51-G51)/F51,0) -> 0.78262785
B52: 47 | C52: Cinnamon Bun Hot Chocolate | D52: S | E52: Hot chocolate | F52: 4 | G52: =IFERROR(VLOOKUP(39,Recipes!$B$7:$G$323,6,FALSE()),0) -> 0.42120411 | H52: =IFERROR((F52-G52)/F52,0) -> 0.89469897
B53: 48 | C53: Cinnamon Bun Hot Chocolate | D53: M | E53: Hot chocolate | F53: 4.2 | G53: =IFERROR(VLOOKUP(38,Recipes!$B$7:$G$323,6,FALSE()),0) -> 0.59913363 | H53: =IFERROR((F53-G53)/F53,0) -> 0.85734914
B54: 49 | C54: Cinnamon Bun Hot Chocolate | D54: XL | E54: Hot chocolate | F54: 4.6 | G54: =IFERROR(VLOOKUP(40,Recipes!$B$7:$G$323,6,FALSE()),0) -> 0.78706314 | H54: =IFERROR((F54-G54)/F54,0) -> 0.82889932
B55: 50 | C55: Cinnamon Bun Latte | D55: S | E55: Latte / flavoured latte | F55: 3.9 | G55: =IFERROR(VLOOKUP(42,Recipes!$B$7:$G$323,6,FALSE()),0) -> 0.83689427 | H55: =IFERROR((F55-G55)/F55,0) -> 0.78541172
B56: 51 | C56: Cinnamon Bun Latte | D56: M | E56: Latte / flavoured latte | F56: 4.1 | G56: =IFERROR(VLOOKUP(41,Recipes!$B$7:$G$323,6,FALSE()),0) -> 0.94482379 | H56: =IFERROR((F56-G56)/F56,0) -> 0.76955517
B57: 52 | C57: Cinnamon Bun Latte | D57: XL | E57: Latte / flavoured latte | F57: 4.5 | G57: =IFERROR(VLOOKUP(43,Recipes!$B$7:$G$323,6,FALSE()),0) -> 1.6037885 | H57: =IFERROR((F57-G57)/F57,0) -> 0.64360255
B58: 53 | C58: Cinnamon classic | D58: M | E58: Cake / sweet | F58: 3 | G58: =IFERROR(VLOOKUP(37,Recipes!$B$7:$G$323,6,FALSE()),0) -> 1.74 | H58: =IFERROR((F58-G58)/F58,0) -> 0.42
B59: 54 | C59: Coca-Cola | D59: M | E59: Bottled / pre-packed | F59: 1.9 | G59: =IFERROR(VLOOKUP(280,Recipes!$B$7:$G$323,6,FALSE()),0) -> 0 | H59: =IFERROR((F59-G59)/F59,0) -> 1
B60: 55 | C60: Coconut milk (+upcharge) | D60: M | E60: Add-on / modifier | F60: 0.5 | G60: =IFERROR(VLOOKUP(281,Recipes!$B$7:$G$323,6,FALSE()),0) -> 0.125 | H60: =IFERROR((F60-G60)/F60,0) -> 0.75
B61: 56 | C61: Coffee Milkshake | D61: S | E61: Milkshake | F61: 4.1 | G61: =IFERROR(VLOOKUP(45,Recipes!$B$7:$G$323,6,FALSE()),0) -> 1.0524119 | H61: =IFERROR((F61-G61)/F61,0) -> 0.74331417
B62: 57 | C62: Coffee Milkshake | D62: M | E62: Milkshake | F62: 4.5 | G62: =IFERROR(VLOOKUP(44,Recipes!$B$7:$G$323,6,FALSE()),0) -> 1.0824119 | H62: =IFERROR((F62-G62)/F62,0) -> 0.75946402
B63: 58 | C63: Cortado | D63: One | E63: Other | F63: 3.1 | G63: =IFERROR(VLOOKUP(46,Recipes!$B$7:$G$323,6,FALSE()),0) -> 0.83689427 | H63: =IFERROR((F63-G63)/F63,0) -> 0.73003411
B64: 59 | C64: Croissant with Jam | D64: M | E64: Food — savoury | F64: 2.5 | G64: =IFERROR(VLOOKUP(282,Recipes!$B$7:$G$323,6,FALSE()),0) -> 0.65 | H64: =IFERROR((F64-G64)/F64,0) -> 0.74
B65: 60 | C65: Dark Blue Wafer | D65: M | E65: Bottled / pre-packed | F65: 1.9 | G65: =IFERROR(VLOOKUP(283,Recipes!$B$7:$G$323,6,FALSE()),0) -> 0 | H65: =IFERROR((F65-G65)/F65,0) -> 1
B66: 61 | C66: Decaf Tea | D66: One | E66: Tea | F66: 1.9 | G66: =IFERROR(VLOOKUP(47,Recipes!$B$7:$G$323,6,FALSE()),0) -> 0.199875 | H66: =IFERROR((F66-G66)/F66,0) -> 0.89480263 | I66: Teas
B67: 62 | C67: Double Espresso | D67: One | E67: Espresso-based | F67: 2 | G67: =IFERROR(VLOOKUP(48,Recipes!$B$7:$G$323,6,FALSE()),0) -> 0.705 | H67: =IFERROR((F67-G67)/F67,0) -> 0.6475
B68: 63 | C68: Double Espresso Con Pana | D68: One | E68: Espresso-based | F68: 2.4 | G68: =IFERROR(VLOOKUP(49,Recipes!$B$7:$G$323,6,FALSE()),0) -> 0.841 | H68: =IFERROR((F68-G68)/F68,0) -> 0.64958333
B69: 64 | C69: Double Macchiato | D69: One | E69: Other | F69: 2.1 | G69: =IFERROR(VLOOKUP(50,Recipes!$B$7:$G$323,6,FALSE()),0) -> 0.81491189 | H69: =IFERROR((F69-G69)/F69,0) -> 0.61194672
B70: 65 | C70: Earl Grey | D70: One | E70: Tea | F70: 1.9 | G70: =IFERROR(VLOOKUP(51,Recipes!$B$7:$G$323,6,FALSE()),0) -> 0.199875 | H70: =IFERROR((F70-G70)/F70,0) -> 0.89480263 | I70: Teas
B71: 66 | C71: Emerald Zest | D71: S | E71: DISCONTINUED (May 2026) | F71: 0 | G71: =IFERROR(VLOOKUP(53,Recipes!$B$7:$G$323,6,FALSE()),0) -> 0 | H71: =IFERROR((F71-G71)/F71,0) -> 0
B72: 67 | C72: Emerald Zest | D72: M | E72: DISCONTINUED (May 2026) | F72: 0 | G72: =IFERROR(VLOOKUP(52,Recipes!$B$7:$G$323,6,FALSE()),0) -> 0 | H72: =IFERROR((F72-G72)/F72,0) -> 0
B73: 68 | C73: English Breakfast | D73: One | E73: Tea | F73: 1.9 | G73: =IFERROR(VLOOKUP(54,Recipes!$B$7:$G$323,6,FALSE()),0) -> 0.199875 | H73: =IFERROR((F73-G73)/F73,0) -> 0.89480263 | I73: Teas
B74: 69 | C74: Espresso Tonic | D74: S | E74: Espresso-based | F74: 3.5 | G74: =IFERROR(VLOOKUP(56,Recipes!$B$7:$G$323,6,FALSE()),0) -> 1.5583333 | H74: =IFERROR((F74-G74)/F74,0) -> 0.5547619
B75: 70 | C75: Espresso Tonic | D75: M | E75: Espresso-based | F75: 3.7 | G75: =IFERROR(VLOOKUP(55,Recipes!$B$7:$G$323,6,FALSE()),0) -> 1.5883333 | H75: =IFERROR((F75-G75)/F75,0) -> 0.57072072
B76: 71 | C76: Extra shot | D76: M | E76: Espresso-based | F76: 0.5 | G76: =IFERROR(VLOOKUP(284,Recipes!$B$7:$G$323,6,FALSE()),0) -> 0.2925 | H76: =IFERROR((F76-G76)/F76,0) -> 0.415
B77: 72 | C77: Fanta | D77: M | E77: Bottled / pre-packed | F77: 1.9 | G77: =IFERROR(VLOOKUP(285,Recipes!$B$7:$G$323,6,FALSE()),0) -> 0 | H77: =IFERROR((F77-G77)/F77,0) -> 1
B78: 73 | C78: Flat White | D78: One | E78: Flat white | F78: 3.25 | G78: =IFERROR(VLOOKUP(57,Recipes!$B$7:$G$323,6,FALSE()),0) -> 0.83689427 | H78: =IFERROR((F78-G78)/F78,0) -> 0.74249407
B79: 74 | C79: Forest Fruits Tea | D79: One | E79: Tea | F79: 2 | G79: =IFERROR(VLOOKUP(58,Recipes!$B$7:$G$323,6,FALSE()),0) -> 0.199875 | H79: =IFERROR((F79-G79)/F79,0) -> 0.9000625
B80: 75 | C80: Ginger and Lemongrass Tea | D80: One | E80: Tea | F80: 2 | G80: =IFERROR(VLOOKUP(59,Recipes!$B$7:$G$323,6,FALSE()),0) -> 0.199875 | H80: =IFERROR((F80-G80)/F80,0) -> 0.9000625
B81: 76 | C81: Green | D81: One | E81: Tea | F81: 1.9 | G81: =IFERROR(VLOOKUP(60,Recipes!$B$7:$G$323,6,FALSE()),0) -> 0.199875 | H81: =IFERROR((F81-G81)/F81,0) -> 0.89480263 | I81: Teas
B82: 77 | C82: Green Apple Bubble Tea | D82: S | E82: Bubble tea | F82: 4.4 | G82: =IFERROR(VLOOKUP(62,Recipes!$B$7:$G$323,6,FALSE()),0) -> 0.55529919 | H82: =IFERROR((F82-G82)/F82,0) -> 0.87379564
B83: 78 | C83: Green Apple Bubble Tea | D83: M | E83: Bubble tea | F83: 4.8 | G83: =IFERROR(VLOOKUP(61,Recipes!$B$7:$G$323,6,FALSE()),0) -> 0.58529919 | H83: =IFERROR((F83-G83)/F83,0) -> 0.87806267
B84: 79 | C84: Ham Croissant | D84: M | E84: Food — savoury | F84: 3.6 | G84: =IFERROR(VLOOKUP(288,Recipes!$B$7:$G$323,6,FALSE()),0) -> 0.65 | H84: =IFERROR((F84-G84)/F84,0) -> 0.81944444
B85: 80 | C85: Ham and Cheese Panini | D85: M | E85: Food — savoury | F85: 4 | G85: =IFERROR(VLOOKUP(286,Recipes!$B$7:$G$323,6,FALSE()),0) -> 0 | H85: =IFERROR((F85-G85)/F85,0) -> 1
B86: 81 | C86: Ham and Cheese Toastie | D86: M | E86: Food — savoury | F86: 4.2 | G86: =IFERROR(VLOOKUP(287,Recipes!$B$7:$G$323,6,FALSE()),0) -> 0 | H86: =IFERROR((F86-G86)/F86,0) -> 1
B87: 82 | C87: Homemade Panini | D87: M | E87: Other | F87: 3.8 | G87: =IFERROR(VLOOKUP(289,Recipes!$B$7:$G$323,6,FALSE()),0) -> 0 | H87: =IFERROR((F87-G87)/F87,0) -> 1
B88: 83 | C88: Homemade Roll | D88: M | E88: Other | F88: 3 | G88: =IFERROR(VLOOKUP(290,Recipes!$B$7:$G$323,6,FALSE()),0) -> 0 | H88: =IFERROR((F88-G88)/F88,0) -> 1
B89: 84 | C89: Honey Bubble Tea | D89: S | E89: Bubble tea | F89: 4.4 | G89: =IFERROR(VLOOKUP(64,Recipes!$B$7:$G$323,6,FALSE()),0) -> 0.74129919 | H89: =IFERROR((F89-G89)/F89,0) -> 0.83152291
B90: 85 | C90: Honey Bubble Tea | D90: M | E90: Bubble tea | F90: 4.8 | G90: =IFERROR(VLOOKUP(63,Recipes!$B$7:$G$323,6,FALSE()),0) -> 0.77129919 | H90: =IFERROR((F90-G90)/F90,0) -> 0.83931267
B91: 86 | C91: Honey Vanilla Latte | D91: S | E91: Latte / flavoured latte | F91: 3.9 | G91: =IFERROR(VLOOKUP(66,Recipes!$B$7:$G$323,6,FALSE()),0) -> 1.0798943 | H91: =IFERROR((F91-G91)/F91,0) -> 0.72310403 | I91: Spring saesonal drinks
B92: 87 | C92: Honey Vanilla Latte | D92: M | E92: Latte / flavoured latte | F92: 4.1 | G92: =IFERROR(VLOOKUP(65,Recipes!$B$7:$G$323,6,FALSE()),0) -> 1.1878238 | H92: =IFERROR((F92-G92)/F92,0) -> 0.71028688 | I92: Spring saesonal drinks
B93: 88 | C93: Honey Vanilla Latte | D93: XL | E93: Latte / flavoured latte | F93: 4.3 | G93: =IFERROR(VLOOKUP(67,Recipes!$B$7:$G$323,6,FALSE()),0) -> 1.8467885 | H93: =IFERROR((F93-G93)/F93,0) -> 0.57051429 | I93: Spring saesonal drinks
B94: 89 | C94: Hot Chocolate | D94: S | E94: Hot chocolate | F94: 3.4 | G94: =IFERROR(VLOOKUP(69,Recipes!$B$7:$G$323,6,FALSE()),0) -> 0.42120411 | H94: =IFERROR((F94-G94)/F94,0) -> 0.87611644
B95: 90 | C95: Hot Chocolate | D95: M | E95: Hot chocolate | F95: 3.7 | G95: =IFERROR(VLOOKUP(68,Recipes!$B$7:$G$323,6,FALSE()),0) -> 0.59913363 | H95: =IFERROR((F95-G95)/F95,0) -> 0.83807199
B96: 91 | C96: Hot Chocolate | D96: XL | E96: Hot chocolate | F96: 4 | G96: =IFERROR(VLOOKUP(70,Recipes!$B$7:$G$323,6,FALSE()),0) -> 0.78706314 | H96: =IFERROR((F96-G96)/F96,0) -> 0.80323421
B97: 92 | C97: Hot Lavender Matcha | D97: S | E97: Matcha | F97: 3.6 | G97: =IFERROR(VLOOKUP(72,Recipes!$B$7:$G$323,6,FALSE()),0) -> 0.94734882 | H97: =IFERROR((F97-G97)/F97,0) -> 0.73684755
B98: 93 | C98: Hot Lavender Matcha | D98: M | E98: Matcha | F98: 3.9 | G98: =IFERROR(VLOOKUP(71,Recipes!$B$7:$G$323,6,FALSE()),0) -> 1.0406234 | H98: =IFERROR((F98-G98)/F98,0) -> 0.73317348
B99: 94 | C99: Hot Lavender Matcha | D99: XL | E99: Matcha | F99: 4.2 | G99: =IFERROR(VLOOKUP(73,Recipes!$B$7:$G$323,6,FALSE()),0) -> 1.143898 | H99: =IFERROR((F99-G99)/F99,0) -> 0.72764333
B100: 95 | C100: Hot Matcha | D100: S | E100: Matcha | F100: 3.4 | G100: =IFERROR(VLOOKUP(75,Recipes!$B$7:$G$323,6,FALSE()),0) -> 0.79734882 | H100: =IFERROR((F100-G100)/F100,0) -> 0.76548564
B101: 96 | C101: Hot Matcha | D101: M | E101: Matcha | F101: 3.7 | G101: =IFERROR(VLOOKUP(74,Recipes!$B$7:$G$323,6,FALSE()),0) -> 0.89062341 | H101: =IFERROR((F101-G101)/F101,0) -> 0.75929097
B102: 97 | C102: Hot Matcha | D102: XL | E102: Matcha | F102: 3.9 | G102: =IFERROR(VLOOKUP(76,Recipes!$B$7:$G$323,6,FALSE()),0) -> 0.99389801 | H102: =IFERROR((F102-G102)/F102,0) -> 0.74515436
...

Sheet Daily Sales
B2: Daily Sales Log
B3: One row per trading day. 'Own cash' auto-fills from Cash Transactions tab if you log there. Otherwise type it in.
B5: Date | C5: Day | D5: Square — card (£) | E5: Square — cash (£) | F5: Own cash (auto from log, £) | G5: Own cash (override, £) | H5: Total revenue (£) | I5: Transactions (Square) | J5: Avg ticket (£) | K5: Notes
B6: 45901 | C6: =IFERROR(TEXT(B6,"ddd"),"") -> Mon | F6: =IFERROR(SUMIFS('Cash Transactions'!F6:F500,'Cash Transactions'!B6:B500,B6),0) -> 0 | H6: =D6+E6+IF(G6>0,G6,F6) -> 0 | J6: =IFERROR(H6/I6,0) -> 0
B7: 45902 | C7: =IFERROR(TEXT(B7,"ddd"),"") -> Tue | F7: =IFERROR(SUMIFS('Cash Transactions'!F6:F500,'Cash Transactions'!B6:B500,B7),0) -> 0 | H7: =D7+E7+IF(G7>0,G7,F7) -> 0 | J7: =IFERROR(H7/I7,0) -> 0
B8: 45903 | C8: =IFERROR(TEXT(B8,"ddd"),"") -> Wed | F8: =IFERROR(SUMIFS('Cash Transactions'!F6:F500,'Cash Transactions'!B6:B500,B8),0) -> 0 | H8: =D8+E8+IF(G8>0,G8,F8) -> 0 | J8: =IFERROR(H8/I8,0) -> 0
B9: 45904 | C9: =IFERROR(TEXT(B9,"ddd"),"") -> Thu | F9: =IFERROR(SUMIFS('Cash Transactions'!F6:F500,'Cash Transactions'!B6:B500,B9),0) -> 0 | H9: =D9+E9+IF(G9>0,G9,F9) -> 0 | J9: =IFERROR(H9/I9,0) -> 0
B10: 45905 | C10: =IFERROR(TEXT(B10,"ddd"),"") -> Fri | F10: =IFERROR(SUMIFS('Cash Transactions'!F6:F500,'Cash Transactions'!B6:B500,B10),0) -> 0 | H10: =D10+E10+IF(G10>0,G10,F10) -> 0 | J10: =IFERROR(H10/I10,0) -> 0
B11: 45906 | C11: =IFERROR(TEXT(B11,"ddd"),"") -> Sat | F11: =IFERROR(SUMIFS('Cash Transactions'!F6:F500,'Cash Transactions'!B6:B500,B11),0) -> 0 | H11: =D11+E11+IF(G11>0,G11,F11) -> 0 | J11: =IFERROR(H11/I11,0) -> 0
B12: 45907 | C12: =IFERROR(TEXT(B12,"ddd"),"") -> Sun | F12: =IFERROR(SUMIFS('Cash Transactions'!F6:F500,'Cash Transactions'!B6:B500,B12),0) -> 0 | H12: =D12+E12+IF(G12>0,G12,F12) -> 0 | J12: =IFERROR(H12/I12,0) -> 0
B13: 45908 | C13: =IFERROR(TEXT(B13,"ddd"),"") -> Mon | F13: =IFERROR(SUMIFS('Cash Transactions'!F6:F500,'Cash Transactions'!B6:B500,B13),0) -> 0 | H13: =D13+E13+IF(G13>0,G13,F13) -> 0 | J13: =IFERROR(H13/I13,0) -> 0
B14: 45909 | C14: =IFERROR(TEXT(B14,"ddd"),"") -> Tue | F14: =IFERROR(SUMIFS('Cash Transactions'!F6:F500,'Cash Transactions'!B6:B500,B14),0) -> 0 | H14: =D14+E14+IF(G14>0,G14,F14) -> 0 | J14: =IFERROR(H14/I14,0) -> 0
B15: 45910 | C15: =IFERROR(TEXT(B15,"ddd"),"") -> Wed | F15: =IFERROR(SUMIFS('Cash Transactions'!F6:F500,'Cash Transactions'!B6:B500,B15),0) -> 0 | H15: =D15+E15+IF(G15>0,G15,F15) -> 0 | J15: =IFERROR(H15/I15,0) -> 0
B16: 45911 | C16: =IFERROR(TEXT(B16,"ddd"),"") -> Thu | F16: =IFERROR(SUMIFS('Cash Transactions'!F6:F500,'Cash Transactions'!B6:B500,B16),0) -> 0 | H16: =D16+E16+IF(G16>0,G16,F16) -> 0 | J16: =IFERROR(H16/I16,0) -> 0
B17: 45912 | C17: =IFERROR(TEXT(B17,"ddd"),"") -> Fri | F17: =IFERROR(SUMIFS('Cash Transactions'!F6:F500,'Cash Transactions'!B6:B500,B17),0) -> 0 | H17: =D17+E17+IF(G17>0,G17,F17) -> 0 | J17: =IFERROR(H17/I17,0) -> 0
B18: 45913 | C18: =IFERROR(TEXT(B18,"ddd"),"") -> Sat | F18: =IFERROR(SUMIFS('Cash Transactions'!F6:F500,'Cash Transactions'!B6:B500,B18),0) -> 0 | H18: =D18+E18+IF(G18>0,G18,F18) -> 0 | J18: =IFERROR(H18/I18,0) -> 0
B19: 45914 | C19: =IFERROR(TEXT(B19,"ddd"),"") -> Sun | F19: =IFERROR(SUMIFS('Cash Transactions'!F6:F500,'Cash Transactions'!B6:B500,B19),0) -> 0 | H19: =D19+E19+IF(G19>0,G19,F19) -> 0 | J19: =IFERROR(H19/I19,0) -> 0
B20: 45915 | C20: =IFERROR(TEXT(B20,"ddd"),"") -> Mon | F20: =IFERROR(SUMIFS('Cash Transactions'!F6:F500,'Cash Transactions'!B6:B500,B20),0) -> 0 | H20: =D20+E20+IF(G20>0,G20,F20) -> 0 | J20: =IFERROR(H20/I20,0) -> 0
B21: 45916 | C21: =IFERROR(TEXT(B21,"ddd"),"") -> Tue | F21: =IFERROR(SUMIFS('Cash Transactions'!F6:F500,'Cash Transactions'!B6:B500,B21),0) -> 0 | H21: =D21+E21+IF(G21>0,G21,F21) -> 0 | J21: =IFERROR(H21/I21,0) -> 0
B22: 45917 | C22: =IFERROR(TEXT(B22,"ddd"),"") -> Wed | F22: =IFERROR(SUMIFS('Cash Transactions'!F6:F500,'Cash Transactions'!B6:B500,B22),0) -> 0 | H22: =D22+E22+IF(G22>0,G22,F22) -> 0 | J22: =IFERROR(H22/I22,0) -> 0
B23: 45918 | C23: =IFERROR(TEXT(B23,"ddd"),"") -> Thu | F23: =IFERROR(SUMIFS('Cash Transactions'!F6:F500,'Cash Transactions'!B6:B500,B23),0) -> 0 | H23: =D23+E23+IF(G23>0,G23,F23) -> 0 | J23: =IFERROR(H23/I23,0) -> 0
B24: 45919 | C24: =IFERROR(TEXT(B24,"ddd"),"") -> Fri | F24: =IFERROR(SUMIFS('Cash Transactions'!F6:F500,'Cash Transactions'!B6:B500,B24),0) -> 0 | H24: =D24+E24+IF(G24>0,G24,F24) -> 0 | J24: =IFERROR(H24/I24,0) -> 0
B25: 45920 | C25: =IFERROR(TEXT(B25,"ddd"),"") -> Sat | F25: =IFERROR(SUMIFS('Cash Transactions'!F6:F500,'Cash Transactions'!B6:B500,B25),0) -> 0 | H25: =D25+E25+IF(G25>0,G25,F25) -> 0 | J25: =IFERROR(H25/I25,0) -> 0
B26: 45921 | C26: =IFERROR(TEXT(B26,"ddd"),"") -> Sun | F26: =IFERROR(SUMIFS('Cash Transactions'!F6:F500,'Cash Transactions'!B6:B500,B26),0) -> 0 | H26: =D26+E26+IF(G26>0,G26,F26) -> 0 | J26: =IFERROR(H26/I26,0) -> 0
B27: 45922 | C27: =IFERROR(TEXT(B27,"ddd"),"") -> Mon | F27: =IFERROR(SUMIFS('Cash Transactions'!F6:F500,'Cash Transactions'!B6:B500,B27),0) -> 0 | H27: =D27+E27+IF(G27>0,G27,F27) -> 0 | J27: =IFERROR(H27/I27,0) -> 0
B28: 45923 | C28: =IFERROR(TEXT(B28,"ddd"),"") -> Tue | F28: =IFERROR(SUMIFS('Cash Transactions'!F6:F500,'Cash Transactions'!B6:B500,B28),0) -> 0 | H28: =D28+E28+IF(G28>0,G28,F28) -> 0 | J28: =IFERROR(H28/I28,0) -> 0
B29: 45924 | C29: =IFERROR(TEXT(B29,"ddd"),"") -> Wed | F29: =IFERROR(SUMIFS('Cash Transactions'!F6:F500,'Cash Transactions'!B6:B500,B29),0) -> 0 | H29: =D29+E29+IF(G29>0,G29,F29) -> 0 | J29: =IFERROR(H29/I29,0) -> 0
B30: 45925 | C30: =IFERROR(TEXT(B30,"ddd"),"") -> Thu | F30: =IFERROR(SUMIFS('Cash Transactions'!F6:F500,'Cash Transactions'!B6:B500,B30),0) -> 0 | H30: =D30+E30+IF(G30>0,G30,F30) -> 0 | J30: =IFERROR(H30/I30,0) -> 0
B31: 45926 | C31: =IFERROR(TEXT(B31,"ddd"),"") -> Fri | F31: =IFERROR(SUMIFS('Cash Transactions'!F6:F500,'Cash Transactions'!B6:B500,B31),0) -> 0 | H31: =D31+E31+IF(G31>0,G31,F31) -> 0 | J31: =IFERROR(H31/I31,0) -> 0
B32: 45927 | C32: =IFERROR(TEXT(B32,"ddd"),"") -> Sat | F32: =IFERROR(SUMIFS('Cash Transactions'!F6:F500,'Cash Transactions'!B6:B500,B32),0) -> 0 | H32: =D32+E32+IF(G32>0,G32,F32) -> 0 | J32: =IFERROR(H32/I32,0) -> 0
B33: 45928 | C33: =IFERROR(TEXT(B33,"ddd"),"") -> Sun | F33: =IFERROR(SUMIFS('Cash Transactions'!F6:F500,'Cash Transactions'!B6:B500,B33),0) -> 0 | H33: =D33+E33+IF(G33>0,G33,F33) -> 0 | J33: =IFERROR(H33/I33,0) -> 0
B34: 45929 | C34: =IFERROR(TEXT(B34,"ddd"),"") -> Mon | F34: =IFERROR(SUMIFS('Cash Transactions'!F6:F500,'Cash Transactions'!B6:B500,B34),0) -> 0 | H34: =D34+E34+IF(G34>0,G34,F34) -> 0 | J34: =IFERROR(H34/I34,0) -> 0
B35: 45930 | C35: =IFERROR(TEXT(B35,"ddd"),"") -> Tue | F35: =IFERROR(SUMIFS('Cash Transactions'!F6:F500,'Cash Transactions'!B6:B500,B35),0) -> 0 | H35: =D35+E35+IF(G35>0,G35,F35) -> 0 | J35: =IFERROR(H35/I35,0) -> 0
B36: 45931 | C36: =IFERROR(TEXT(B36,"ddd"),"") -> Wed | F36: =IFERROR(SUMIFS('Cash Transactions'!F6:F500,'Cash Transactions'!B6:B500,B36),0) -> 0 | H36: =D36+E36+IF(G36>0,G36,F36) -> 0 | J36: =IFERROR(H36/I36,0) -> 0
B37: 45932 | C37: =IFERROR(TEXT(B37,"ddd"),"") -> Thu | F37: =IFERROR(SUMIFS('Cash Transactions'!F6:F500,'Cash Transactions'!B6:B500,B37),0) -> 0 | H37: =D37+E37+IF(G37>0,G37,F37) -> 0 | J37: =IFERROR(H37/I37,0) -> 0
B38: 45933 | C38: =IFERROR(TEXT(B38,"ddd"),"") -> Fri | F38: =IFERROR(SUMIFS('Cash Transactions'!F6:F500,'Cash Transactions'!B6:B500,B38),0) -> 0 | H38: =D38+E38+IF(G38>0,G38,F38) -> 0 | J38: =IFERROR(H38/I38,0) -> 0
B39: 45934 | C39: =IFERROR(TEXT(B39,"ddd"),"") -> Sat | F39: =IFERROR(SUMIFS('Cash Transactions'!F6:F500,'Cash Transactions'!B6:B500,B39),0) -> 0 | H39: =D39+E39+IF(G39>0,G39,F39) -> 0 | J39: =IFERROR(H39/I39,0) -> 0
B40: 45935 | C40: =IFERROR(TEXT(B40,"ddd"),"") -> Sun | F40: =IFERROR(SUMIFS('Cash Transactions'!F6:F500,'Cash Transactions'!B6:B500,B40),0) -> 0 | H40: =D40+E40+IF(G40>0,G40,F40) -> 0 | J40: =IFERROR(H40/I40,0) -> 0
B41: 45936 | C41: =IFERROR(TEXT(B41,"ddd"),"") -> Mon | F41: =IFERROR(SUMIFS('Cash Transactions'!F6:F500,'Cash Transactions'!B6:B500,B41),0) -> 0 | H41: =D41+E41+IF(G41>0,G41,F41) -> 0 | J41: =IFERROR(H41/I41,0) -> 0
B42: 45937 | C42: =IFERROR(TEXT(B42,"ddd"),"") -> Tue | F42: =IFERROR(SUMIFS('Cash Transactions'!F6:F500,'Cash Transactions'!B6:B500,B42),0) -> 0 | H42: =D42+E42+IF(G42>0,G42,F42) -> 0 | J42: =IFERROR(H42/I42,0) -> 0
B43: 45938 | C43: =IFERROR(TEXT(B43,"ddd"),"") -> Wed | F43: =IFERROR(SUMIFS('Cash Transactions'!F6:F500,'Cash Transactions'!B6:B500,B43),0) -> 0 | H43: =D43+E43+IF(G43>0,G43,F43) -> 0 | J43: =IFERROR(H43/I43,0) -> 0
B44: 45939 | C44: =IFERROR(TEXT(B44,"ddd"),"") -> Thu | F44: =IFERROR(SUMIFS('Cash Transactions'!F6:F500,'Cash Transactions'!B6:B500,B44),0) -> 0 | H44: =D44+E44+IF(G44>0,G44,F44) -> 0 | J44: =IFERROR(H44/I44,0) -> 0
B45: 45940 | C45: =IFERROR(TEXT(B45,"ddd"),"") -> Fri | F45: =IFERROR(SUMIFS('Cash Transactions'!F6:F500,'Cash Transactions'!B6:B500,B45),0) -> 0 | H45: =D45+E45+IF(G45>0,G45,F45) -> 0 | J45: =IFERROR(H45/I45,0) -> 0
B46: 45941 | C46: =IFERROR(TEXT(B46,"ddd"),"") -> Sat | F46: =IFERROR(SUMIFS('Cash Transactions'!F6:F500,'Cash Transactions'!B6:B500,B46),0) -> 0 | H46: =D46+E46+IF(G46>0,G46,F46) -> 0 | J46: =IFERROR(H46/I46,0) -> 0
B47: 45942 | C47: =IFERROR(TEXT(B47,"ddd"),"") -> Sun | F47: =IFERROR(SUMIFS('Cash Transactions'!F6:F500,'Cash Transactions'!B6:B500,B47),0) -> 0 | H47: =D47+E47+IF(G47>0,G47,F47) -> 0 | J47: =IFERROR(H47/I47,0) -> 0
B48: 45943 | C48: =IFERROR(TEXT(B48,"ddd"),"") -> Mon | F48: =IFERROR(SUMIFS('Cash Transactions'!F6:F500,'Cash Transactions'!B6:B500,B48),0) -> 0 | H48: =D48+E48+IF(G48>0,G48,F48) -> 0 | J48: =IFERROR(H48/I48,0) -> 0
B49: 45944 | C49: =IFERROR(TEXT(B49,"ddd"),"") -> Tue | F49: =IFERROR(SUMIFS('Cash Transactions'!F6:F500,'Cash Transactions'!B6:B500,B49),0) -> 0 | H49: =D49+E49+IF(G49>0,G49,F49) -> 0 | J49: =IFERROR(H49/I49,0) -> 0
B50: 45945 | C50: =IFERROR(TEXT(B50,"ddd"),"") -> Wed | F50: =IFERROR(SUMIFS('Cash Transactions'!F6:F500,'Cash Transactions'!B6:B500,B50),0) -> 0 | H50: =D50+E50+IF(G50>0,G50,F50) -> 0 | J50: =IFERROR(H50/I50,0) -> 0
B51: 45946 | C51: =IFERROR(TEXT(B51,"ddd"),"") -> Thu | F51: =IFERROR(SUMIFS('Cash Transactions'!F6:F500,'Cash Transactions'!B6:B500,B51),0) -> 0 | H51: =D51+E51+IF(G51>0,G51,F51) -> 0 | J51: =IFERROR(H51/I51,0) -> 0
B52: 45947 | C52: =IFERROR(TEXT(B52,"ddd"),"") -> Fri | F52: =IFERROR(SUMIFS('Cash Transactions'!F6:F500,'Cash Transactions'!B6:B500,B52),0) -> 0 | H52: =D52+E52+IF(G52>0,G52,F52) -> 0 | J52: =IFERROR(H52/I52,0) -> 0
B53: 45948 | C53: =IFERROR(TEXT(B53,"ddd"),"") -> Sat | F53: =IFERROR(SUMIFS('Cash Transactions'!F6:F500,'Cash Transactions'!B6:B500,B53),0) -> 0 | H53: =D53+E53+IF(G53>0,G53,F53) -> 0 | J53: =IFERROR(H53/I53,0) -> 0
B54: 45949 | C54: =IFERROR(TEXT(B54,"ddd"),"") -> Sun | F54: =IFERROR(SUMIFS('Cash Transactions'!F6:F500,'Cash Transactions'!B6:B500,B54),0) -> 0 | H54: =D54+E54+IF(G54>0,G54,F54) -> 0 | J54: =IFERROR(H54/I54,0) -> 0
B55: 45950 | C55: =IFERROR(TEXT(B55,"ddd"),"") -> Mon | F55: =IFERROR(SUMIFS('Cash Transactions'!F6:F500,'Cash Transactions'!B6:B500,B55),0) -> 0 | H55: =D55+E55+IF(G55>0,G55,F55) -> 0 | J55: =IFERROR(H55/I55,0) -> 0
B56: 45951 | C56: =IFERROR(TEXT(B56,"ddd"),"") -> Tue | F56: =IFERROR(SUMIFS('Cash Transactions'!F6:F500,'Cash Transactions'!B6:B500,B56),0) -> 0 | H56: =D56+E56+IF(G56>0,G56,F56) -> 0 | J56: =IFERROR(H56/I56,0) -> 0
B57: 45952 | C57: =IFERROR(TEXT(B57,"ddd"),"") -> Wed | F57: =IFERROR(SUMIFS('Cash Transactions'!F6:F500,'Cash Transactions'!B6:B500,B57),0) -> 0 | H57: =D57+E57+IF(G57>0,G57,F57) -> 0 | J57: =IFERROR(H57/I57,0) -> 0
B58: 45953 | C58: =IFERROR(TEXT(B58,"ddd"),"") -> Thu | F58: =IFERROR(SUMIFS('Cash Transactions'!F6:F500,'Cash Transactions'!B6:B500,B58),0) -> 0 | H58: =D58+E58+IF(G58>0,G58,F58) -> 0 | J58: =IFERROR(H58/I58,0) -> 0
B59: 45954 | C59: =IFERROR(TEXT(B59,"ddd"),"") -> Fri | F59: =IFERROR(SUMIFS('Cash Transactions'!F6:F500,'Cash Transactions'!B6:B500,B59),0) -> 0 | H59: =D59+E59+IF(G59>0,G59,F59) -> 0 | J59: =IFERROR(H59/I59,0) -> 0
B60: 45955 | C60: =IFERROR(TEXT(B60,"ddd"),"") -> Sat | F60: =IFERROR(SUMIFS('Cash Transactions'!F6:F500,'Cash Transactions'!B6:B500,B60),0) -> 0 | H60: =D60+E60+IF(G60>0,G60,F60) -> 0 | J60: =IFERROR(H60/I60,0) -> 0
B61: 45956 | C61: =IFERROR(TEXT(B61,"ddd"),"") -> Sun | D61: 0.98 | F61: =IFERROR(SUMIFS('Cash Transactions'!F6:F500,'Cash Transactions'!B6:B500,B61),0) -> 0 | H61: =D61+E61+IF(G61>0,G61,F61) -> 0.98 | J61: =IFERROR(H61/I61,0) -> 0
B62: 45957 | C62: =IFERROR(TEXT(B62,"ddd"),"") -> Mon | F62: =IFERROR(SUMIFS('Cash Transactions'!F6:F500,'Cash Transactions'!B6:B500,B62),0) -> 0 | H62: =D62+E62+IF(G62>0,G62,F62) -> 0 | J62: =IFERROR(H62/I62,0) -> 0
B63: 45958 | C63: =IFERROR(TEXT(B63,"ddd"),"") -> Tue | F63: =IFERROR(SUMIFS('Cash Transactions'!F6:F500,'Cash Transactions'!B6:B500,B63),0) -> 0 | H63: =D63+E63+IF(G63>0,G63,F63) -> 0 | J63: =IFERROR(H63/I63,0) -> 0
B64: 45959 | C64: =IFERROR(TEXT(B64,"ddd"),"") -> Wed | F64: =IFERROR(SUMIFS('Cash Transactions'!F6:F500,'Cash Transactions'!B6:B500,B64),0) -> 0 | H64: =D64+E64+IF(G64>0,G64,F64) -> 0 | J64: =IFERROR(H64/I64,0) -> 0
B65: 45960 | C65: =IFERROR(TEXT(B65,"ddd"),"") -> Thu | F65: =IFERROR(SUMIFS('Cash Transactions'!F6:F500,'Cash Transactions'!B6:B500,B65),0) -> 0 | H65: =D65+E65+IF(G65>0,G65,F65) -> 0 | J65: =IFERROR(H65/I65,0) -> 0
B66: 45961 | C66: =IFERROR(TEXT(B66,"ddd"),"") -> Fri | F66: =IFERROR(SUMIFS('Cash Transactions'!F6:F500,'Cash Transactions'!B6:B500,B66),0) -> 0 | H66: =D66+E66+IF(G66>0,G66,F66) -> 0 | J66: =IFERROR(H66/I66,0) -> 0
B67: 45962 | C67: =IFERROR(TEXT(B67,"ddd"),"") -> Sat | F67: =IFERROR(SUMIFS('Cash Transactions'!F6:F500,'Cash Transactions'!B6:B500,B67),0) -> 0 | H67: =D67+E67+IF(G67>0,G67,F67) -> 0 | J67: =IFERROR(H67/I67,0) -> 0
B68: 45963 | C68: =IFERROR(TEXT(B68,"ddd"),"") -> Sun | F68: =IFERROR(SUMIFS('Cash Transactions'!F6:F500,'Cash Transactions'!B6:B500,B68),0) -> 0 | H68: =D68+E68+IF(G68>0,G68,F68) -> 0 | J68: =IFERROR(H68/I68,0) -> 0
B69: 45964 | C69: =IFERROR(TEXT(B69,"ddd"),"") -> Mon | F69: =IFERROR(SUMIFS('Cash Transactions'!F6:F500,'Cash Transactions'!B6:B500,B69),0) -> 0 | H69: =D69+E69+IF(G69>0,G69,F69) -> 0 | J69: =IFERROR(H69/I69,0) -> 0
B70: 45965 | C70: =IFERROR(TEXT(B70,"ddd"),"") -> Tue | F70: =IFERROR(SUMIFS('Cash Transactions'!F6:F500,'Cash Transactions'!B6:B500,B70),0) -> 0 | H70: =D70+E70+IF(G70>0,G70,F70) -> 0 | J70: =IFERROR(H70/I70,0) -> 0
B71: 45966 | C71: =IFERROR(TEXT(B71,"ddd"),"") -> Wed | D71: 3.92 | F71: =IFERROR(SUMIFS('Cash Transactions'!F6:F500,'Cash Transactions'!B6:B500,B71),0) -> 0 | H71: =D71+E71+IF(G71>0,G71,F71) -> 3.92 | J71: =IFERROR(H71/I71,0) -> 0
B72: 45967 | C72: =IFERROR(TEXT(B72,"ddd"),"") -> Thu | F72: =IFERROR(SUMIFS('Cash Transactions'!F6:F500,'Cash Transactions'!B6:B500,B72),0) -> 0 | H72: =D72+E72+IF(G72>0,G72,F72) -> 0 | J72: =IFERROR(H72/I72,0) -> 0
B73: 45968 | C73: =IFERROR(TEXT(B73,"ddd"),"") -> Fri | F73: =IFERROR(SUMIFS('Cash Transactions'!F6:F500,'Cash Transactions'!B6:B500,B73),0) -> 0 | H73: =D73+E73+IF(G73>0,G73,F73) -> 0 | J73: =IFERROR(H73/I73,0) -> 0
B74: 45969 | C74: =IFERROR(TEXT(B74,"ddd"),"") -> Sat | D74: 283.69 | F74: =IFERROR(SUMIFS('Cash Transactions'!F6:F500,'Cash Transactions'!B6:B500,B74),0) -> 0 | H74: =D74+E74+IF(G74>0,G74,F74) -> 283.69 | J74: =IFERROR(H74/I74,0) -> 0
B75: 45970 | C75: =IFERROR(TEXT(B75,"ddd"),"") -> Sun | D75: 107.16 | F75: =IFERROR(SUMIFS('Cash Transactions'!F6:F500,'Cash Transactions'!B6:B500,B75),0) -> 0 | H75: =D75+E75+IF(G75>0,G75,F75) -> 107.16 | J75: =IFERROR(H75/I75,0) -> 0
B76: 45971 | C76: =IFERROR(TEXT(B76,"ddd"),"") -> Mon | D76: 41.8 | F76: =IFERROR(SUMIFS('Cash Transactions'!F6:F500,'Cash Transactions'!B6:B500,B76),0) -> 0 | H76: =D76+E76+IF(G76>0,G76,F76) -> 41.8 | J76: =IFERROR(H76/I76,0) -> 0
B77: 45972 | C77: =IFERROR(TEXT(B77,"ddd"),"") -> Tue | D77: 121.01 | F77: =IFERROR(SUMIFS('Cash Transactions'!F6:F500,'Cash Transactions'!B6:B500,B77),0) -> 0 | H77: =D77+E77+IF(G77>0,G77,F77) -> 121.01 | J77: =IFERROR(H77/I77,0) -> 0
B78: 45973 | C78: =IFERROR(TEXT(B78,"ddd"),"") -> Wed | D78: 40.49 | F78: =IFERROR(SUMIFS('Cash Transactions'!F6:F500,'Cash Transactions'!B6:B500,B78),0) -> 0 | H78: =D78+E78+IF(G78>0,G78,F78) -> 40.49 | J78: =IFERROR(H78/I78,0) -> 0
B79: 45974 | C79: =IFERROR(TEXT(B79,"ddd"),"") -> Thu | D79: 70.69 | F79: =IFERROR(SUMIFS('Cash Transactions'!F6:F500,'Cash Transactions'!B6:B500,B79),0) -> 0 | H79: =D79+E79+IF(G79>0,G79,F79) -> 70.69 | J79: =IFERROR(H79/I79,0) -> 0
B80: 45975 | C80: =IFERROR(TEXT(B80,"ddd"),"") -> Fri | D80: 27.81 | F80: =IFERROR(SUMIFS('Cash Transactions'!F6:F500,'Cash Transactions'!B6:B500,B80),0) -> 0 | H80: =D80+E80+IF(G80>0,G80,F80) -> 27.81 | J80: =IFERROR(H80/I80,0) -> 0
B81: 45976 | C81: =IFERROR(TEXT(B81,"ddd"),"") -> Sat | D81: 101.35 | F81: =IFERROR(SUMIFS('Cash Transactions'!F6:F500,'Cash Transactions'!B6:B500,B81),0) -> 0 | H81: =D81+E81+IF(G81>0,G81,F81) -> 101.35 | J81: =IFERROR(H81/I81,0) -> 0
B82: 45977 | C82: =IFERROR(TEXT(B82,"ddd"),"") -> Sun | D82: 181.26 | F82: =IFERROR(SUMIFS('Cash Transactions'!F6:F500,'Cash Transactions'!B6:B500,B82),0) -> 0 | H82: =D82+E82+IF(G82>0,G82,F82) -> 181.26 | J82: =IFERROR(H82/I82,0) -> 0
B83: 45978 | C83: =IFERROR(TEXT(B83,"ddd"),"") -> Mon | D83: 66.27 | F83: =IFERROR(SUMIFS('Cash Transactions'!F6:F500,'Cash Transactions'!B6:B500,B83),0) -> 0 | H83: =D83+E83+IF(G83>0,G83,F83) -> 66.27 | J83: =IFERROR(H83/I83,0) -> 0
B84: 45979 | C84: =IFERROR(TEXT(B84,"ddd"),"") -> Tue | D84: 88.13 | F84: =IFERROR(SUMIFS('Cash Transactions'!F6:F500,'Cash Transactions'!B6:B500,B84),0) -> 0 | H84: =D84+E84+IF(G84>0,G84,F84) -> 88.13 | J84: =IFERROR(H84/I84,0) -> 0
B85: 45980 | C85: =IFERROR(TEXT(B85,"ddd"),"") -> Wed | D85: 81.3 | F85: =IFERROR(SUMIFS('Cash Transactions'!F6:F500,'Cash Transactions'!B6:B500,B85),0) -> 0 | H85: =D85+E85+IF(G85>0,G85,F85) -> 81.3 | J85: =IFERROR(H85/I85,0) -> 0
B86: 45981 | C86: =IFERROR(TEXT(B86,"ddd"),"") -> Thu | D86: 105.47 | F86: =IFERROR(SUMIFS('Cash Transactions'!F6:F500,'Cash Transactions'!B6:B500,B86),0) -> 0 | H86: =D86+E86+IF(G86>0,G86,F86) -> 105.47 | J86: =IFERROR(H86/I86,0) -> 0
B87: 45982 | C87: =IFERROR(TEXT(B87,"ddd"),"") -> Fri | D87: 116.33 | F87: =IFERROR(SUMIFS('Cash Transactions'!F6:F500,'Cash Transactions'!B6:B500,B87),0) -> 0 | H87: =D87+E87+IF(G87>0,G87,F87) -> 116.33 | J87: =IFERROR(H87/I87,0) -> 0
B88: 45983 | C88: =IFERROR(TEXT(B88,"ddd"),"") -> Sat | D88: 82.79 | F88: =IFERROR(SUMIFS('Cash Transactions'!F6:F500,'Cash Transactions'!B6:B500,B88),0) -> 0 | H88: =D88+E88+IF(G88>0,G88,F88) -> 82.79 | J88: =IFERROR(H88/I88,0) -> 0
B89: 45984 | C89: =IFERROR(TEXT(B89,"ddd"),"") -> Sun | D89: 71.18 | F89: =IFERROR(SUMIFS('Cash Transactions'!F6:F500,'Cash Transactions'!B6:B500,B89),0) -> 0 | H89: =D89+E89+IF(G89>0,G89,F89) -> 71.18 | J89: =IFERROR(H89/I89,0) -> 0
B90: 45985 | C90: =IFERROR(TEXT(B90,"ddd"),"") -> Mon | D90: 56.44 | F90: =IFERROR(SUMIFS('Cash Transactions'!F6:F500,'Cash Transactions'!B6:B500,B90),0) -> 0 | H90: =D90+E90+IF(G90>0,G90,F90) -> 56.44 | J90: =IFERROR(H90/I90,0) -> 0
B91: 45986 | C91: =IFERROR(TEXT(B91,"ddd"),"") -> Tue | D91: 56.46 | F91: =IFERROR(SUMIFS('Cash Transactions'!F6:F500,'Cash Transactions'!B6:B500,B91),0) -> 0 | H91: =D91+E91+IF(G91>0,G91,F91) -> 56.46 | J91: =IFERROR(H91/I91,0) -> 0
B92: 45987 | C92: =IFERROR(TEXT(B92,"ddd"),"") -> Wed | D92: 40.92 | F92: =IFERROR(SUMIFS('Cash Transactions'!F6:F500,'Cash Transactions'!B6:B500,B92),0) -> 0 | H92: =D92+E92+IF(G92>0,G92,F92) -> 40.92 | J92: =IFERROR(H92/I92,0) -> 0
B93: 45988 | C93: =IFERROR(TEXT(B93,"ddd"),"") -> Thu | F93: =IFERROR(SUMIFS('Cash Transactions'!F6:F500,'Cash Transactions'!B6:B500,B93),0) -> 0 | H93: =D93+E93+IF(G93>0,G93,F93) -> 0 | J93: =IFERROR(H93/I93,0) -> 0
B94: 45989 | C94: =IFERROR(TEXT(B94,"ddd"),"") -> Fri | E94: 29.62 | F94: =IFERROR(SUMIFS('Cash Transactions'!F6:F500,'Cash Transactions'!B6:B500,B94),0) -> 0 | H94: =D94+E94+IF(G94>0,G94,F94) -> 29.62 | J94: =IFERROR(H94/I94,0) -> 0 | K94: Just Eat: £29.62
B95: 45990 | C95: =IFERROR(TEXT(B95,"ddd"),"") -> Sat | F95: =IFERROR(SUMIFS('Cash Transactions'!F6:F500,'Cash Transactions'!B6:B500,B95),0) -> 0 | H95: =D95+E95+IF(G95>0,G95,F95) -> 0 | J95: =IFERROR(H95/I95,0) -> 0
B96: 45991 | C96: =IFERROR(TEXT(B96,"ddd"),"") -> Sun | F96: =IFERROR(SUMIFS('Cash Transactions'!F6:F500,'Cash Transactions'!B6:B500,B96),0) -> 0 | H96: =D96+E96+IF(G96>0,G96,F96) -> 0 | J96: =IFERROR(H96/I96,0) -> 0
B97: 45992 | C97: =IFERROR(TEXT(B97,"ddd"),"") -> Mon | F97: =IFERROR(SUMIFS('Cash Transactions'!F6:F500,'Cash Transactions'!B6:B500,B97),0) -> 0 | H97: =D97+E97+IF(G97>0,G97,F97) -> 0 | J97: =IFERROR(H97/I97,0) -> 0
B98: 45993 | C98: =IFERROR(TEXT(B98,"ddd"),"") -> Tue | D98: 60.57 | F98: =IFERROR(SUMIFS('Cash Transactions'!F6:F500,'Cash Transactions'!B6:B500,B98),0) -> 0 | H98: =D98+E98+IF(G98>0,G98,F98) -> 60.57 | J98: =IFERROR(H98/I98,0) -> 0
B99: 45994 | C99: =IFERROR(TEXT(B99,"ddd"),"") -> Wed | D99: 85.14 | F99: =IFERROR(SUMIFS('Cash Transactions'!F6:F500,'Cash Transactions'!B6:B500,B99),0) -> 0 | H99: =D99+E99+IF(G99>0,G99,F99) -> 85.14 | J99: =IFERROR(H99/I99,0) -> 0
B100: 45995 | C100: =IFERROR(TEXT(B100,"ddd"),"") -> Thu | D100: 59.58 | F100: =IFERROR(SUMIFS('Cash Transactions'!F6:F500,'Cash Transactions'!B6:B500,B100),0) -> 0 | H100: =D100+E100+IF(G100>0,G100,F100) -> 59.58 | J100: =IFERROR(H100/I100,0) -> 0
B101: 45996 | C101: =IFERROR(TEXT(B101,"ddd"),"") -> Fri | D101: 65.19 | F101: =IFERROR(SUMIFS('Cash Transactions'!F6:F500,'Cash Transactions'!B6:B500,B101),0) -> 0 | H101: =D101+E101+IF(G101>0,G101,F101) -> 65.19 | J101: =IFERROR(H101/I101,0) -> 0
B102: 45997 | C102: =IFERROR(TEXT(B102,"ddd"),"") -> Sat | D102: 23.54 | F102: =IFERROR(SUMIFS('Cash Transactions'!F6:F500,'Cash Transactions'!B6:B500,B102),0) -> 0 | H102: =D102+E102+IF(G102>0,G102,F102) -> 23.54 | J102: =IFERROR(H102/I102,0) -> 0
...

Sheet Cash Transactions
B2: Cash Transactions Log
B3: Log cash sales that didn't go through Square. Item dropdown from your menu. Totals feed Daily Sales automatically.
B5: Date | C5: Item (dropdown) | D5: Qty | E5: Unit price (£) | F5: Total (£) | G5: Notes | L5: 'card' (£3.00) (M)
F6: =IFERROR(D6*E6,0) -> 0 | L6: Afternoon Deal (M)
F7: =IFERROR(D7*E7,0) -> 0 | L7: Apple Juice (M)
F8: =IFERROR(D8*E8,0) -> 0 | L8: BKK Kyiv cake (M)
F9: =IFERROR(D9*E9,0) -> 0 | L9: Babyccino (M)
F10: =IFERROR(D10*E10,0) -> 0 | L10: Banana Milkshake (M)
F11: =IFERROR(D11*E11,0) -> 0 | L11: Banana Milkshake (S)
F12: =IFERROR(D12*E12,0) -> 0 | L12: Banana and Pecan Muffin (M)
F13: =IFERROR(D13*E13,0) -> 0 | L13: Berry Breeze Lemonade (M)
F14: =IFERROR(D14*E14,0) -> 0 | L14: Berry Breeze Lemonade (S)
F15: =IFERROR(D15*E15,0) -> 0 | L15: Berry Tea (One)
F16: =IFERROR(D16*E16,0) -> 0 | L16: Billionaire's shortbread (M)
F17: =IFERROR(D17*E17,0) -> 0 | L17: Black Americano (M)
... F318: =IFERROR(D318*E318,0) -> 0 | L318: White Mocha (XL)
F319: =IFERROR(D319*E319,0) -> 0
F320: =IFERROR(D320*E320,0) -> 0
F321: =IFERROR(D321*E321,0) -> 0
F322: =IFERROR(D322*E322,0) -> 0
F323: =IFERROR(D323*E323,0) -> 0
F324: =IFERROR(D324*E324,0) -> 0
F325: =IFERROR(D325*E325,0) -> 0
F326: =IFERROR(D326*E326,0) -> 0
F327: =IFERROR(D327*E327,0) -> 0
F328: =IFERROR(D328*E328,0) -> 0
F329: =IFERROR(D329*E329,0) -> 0
F330: =IFERROR(D330*E330,0) -> 0
... F500: =IFERROR(D500*E500,0) -> 0

Sheet Expenses
B2: Expenses Log
B3: All business outgoings. Use consistent category names — the P&L groups by these.
B5: Date | C5: Category | D5: Vendor / description | E5: Amount (£) | F5: Payment method | G5: Receipt? | H5: Notes | L5: Stock — coffee
B6: 45938 | C6: Other | D6: Nextdaycatering.co.uk Card purchase | E6: 870.78 | F6: Card | H6: Capital expenditure — Catering equipment (capital expense, not regular) | L6: Stock — dairy
B7: 45944 | C7: Other | D7: Inv-2076 Call Out Dale Morrison Bank transfer | E7: 75 | F7: Bank transfer | H7: Capital expenditure — Setup/maintenance work (capital expense) | L7: Stock — syrups
B8: 45944 | C8: Other | D8: Adexa Direct Card purchase | E8: 715.39 | F8: Card | H8: Capital expenditure — Catering equipment (capital expense, not regular) | L8: Stock — cakes
B9: 45951 | C9: Other | D9: Royal Bk Of Scotland Dundee Gbr Withdrawal | E9: 200 | F9: Cash withdrawal | H9: Director drawings — cash withdrawal | L9: Stock — food
B10: 45954 | C10: Utilities | D10: Efx076648 Everﬂow Limited Direct debit | E10: 92.13 | F10: Direct debit | H10: Water | L10: Stock — packaging
B11: 45964 | C11: Rent | D11: 23com Rent Nethergate Lettings Ltd Standing order | E11: 625 | F11: Standing order | H11: Monthly rent | L11: Stock — other
B12: 45965 | C12: Other | D12: Drem01- 44638 Chas Stewart Plumbing Heat Bank transfer | E12: 858 | F12: Bank transfer | H12: Capital expenditure — Setup/maintenance work (capital expense) | L12: Rent
B13: 45969 | C13: Utilities | D13: Bt Business Bill Card purchase | E13: 10.79 | F13: Card | H13: Phone/internet (BT) | L13: Utilities
B14: 45971 | C14: Utilities | D14: 2000322410001 Yu Energy Direct debit | E14: 39 | F14: Direct debit | H14: Electricity | L14: Wages
B15: 45978 | C15: Stock — food | D15: 2028660 Sysco Gb Direct debit | E15: 243.28 | F15: Direct debit | H15: Sysco — likely fresh food/dairy mix; could be split if needed | L15: Marketing
B16: 45984 | C16: Other | D16: Anduff Car Wash Limite Buckinghamshi Gbr Card purchase | E16: 13 | F16: Card | H16: Director drawings — Car wash — personal | L16: Square fees
B17: 45984 | C17: Stock — food | D17: Kyivsmak Card purchase | E17: 48.87 | F17: Card | H17: Kyivsmak — Ukrainian food supplier | L17: Other
B18: 45984 | C18: Stock — food | D18: Tesco Card purchase | E18: 66.8 | F18: Card | H18: Supermarket purchase — likely stock for shop
B19: 45984 | C19: Other | D19: Forfar Road Service St Scotland Card purchase | E19: 82.89 | F19: Card | H19: Director drawings — Travel — likely personal
B20: 45984 | C20: Stock — food | D20: Morrisons Daily Card purchase | E20: 41.3 | F20: Card | H20: Supermarket purchase — likely stock for shop
B21: 45984 | C21: Other | D21: Nya Scotia Forecourt S Dundee Card purchase | E21: 3 | F21: Card | H21: Director drawings — Personal
B22: 45985 | C22: Stock — food | D22: 2028660 Sysco Gb Direct debit | E22: 281.89 | F22: Direct debit | H22: Sysco — likely fresh food/dairy mix; could be split if needed
B23: 45985 | C23: Utilities | D23: Efx076648 Everﬂow Limited Direct debit | E23: 92.12 | F23: Direct debit | H23: Water
B24: 45985 | C24: Stock — food | D24: Lidl Card purchase | E24: 40.89 | F24: Card | H24: Supermarket purchase — likely stock for shop
B25: 45985 | C25: Other | D25: Dundee Cc Parking Card purchase | E25: 4 | F25: Card | H25: Director drawings — Parking — personal
B26: 45985 | C26: Other | D26: Tenpin Dundee Card purchase | E26: 18.5 | F26: Card | H26: Director drawings — Personal expenditure on business card
B27: 45985 | C27: Other | D27: David Lloyds Leisure L Dundee Card purchase | E27: 3.46 | F27: Card | H27: Director drawings — Personal expenditure on business card
B28: 45986 | C28: Stock — other | D28: Mol Ndcc Card purchase | E28: 122.91 | F28: Card | H28: Mol Ndcc — ASK USER what this is
B29: 45986 | C29: Stock — food | D29: Lidl Card purchase | E29: 48.74 | F29: Card | H29: Supermarket purchase — likely stock for shop
... B154: 46112 | C154: Stock — other | D154: Mol Ndcc Card purchase | E154: 163.62 | F154: Card | H154: Mol Ndcc — ASK USER what this is

Sheet Monthly P&L
B2: Monthly Profit & Loss — Full Year View
B3: Every month side-by-side. Change the year in yellow to see a different year. Total column auto-sums.
B5: Year: | C5: 2026
B7: Line | C7: Jan | D7: Feb | E7: Mar | F7: Apr | G7: May | H7: Jun | I7: Jul | J7: Aug | K7: Sep | L7: Oct | M7: Nov | N7: Dec | O7: TOTAL
B8: REVENUE
B9: Card sales | C9: =SUMPRODUCT((MONTH('Daily Sales'!$B$6:$B$371)=1)*(YEAR('Daily Sales'!$B$6:$B$371)=$C$5)*'Daily Sales'!$D$6:$D$371) -> 1789.8 | D9: =SUMPRODUCT((MONTH('Daily Sales'!$B$6:$B$371)=2)*(YEAR('Daily Sales'!$B$6:$B$371)=$C$5)*'Daily Sales'!$D$6:$D$371) -> 1712.7 | E9: =SUMPRODUCT((MONTH('Daily Sales'!$B$6:$B$371)=3)*(YEAR('Daily Sales'!$B$6:$B$371)=$C$5)*'Daily Sales'!$D$6:$D$371) -> 2405.44 | F9: =SUMPRODUCT((MONTH('Daily Sales'!$B$6:$B$371)=4)*(YEAR('Daily Sales'!$B$6:$B$371)=$C$5)*'Daily Sales'!$D$6:$D$371) -> 1293.05 | G9: =SUMPRODUCT((MONTH('Daily Sales'!$B$6:$B$371)=5)*(YEAR('Daily Sales'!$B$6:$B$371)=$C$5)*'Daily Sales'!$D$6:$D$371) -> 0 | H9: =SUMPRODUCT((MONTH('Daily Sales'!$B$6:$B$371)=6)*(YEAR('Daily Sales'!$B$6:$B$371)=$C$5)*'Daily Sales'!$D$6:$D$371) -> 0 | I9: =SUMPRODUCT((MONTH('Daily Sales'!$B$6:$B$371)=7)*(YEAR('Daily Sales'!$B$6:$B$371)=$C$5)*'Daily Sales'!$D$6:$D$371) -> 0 | J9: =SUMPRODUCT((MONTH('Daily Sales'!$B$6:$B$371)=8)*(YEAR('Daily Sales'!$B$6:$B$371)=$C$5)*'Daily Sales'!$D$6:$D$371) -> 0 | K9: =SUMPRODUCT((MONTH('Daily Sales'!$B$6:$B$371)=9)*(YEAR('Daily Sales'!$B$6:$B$371)=$C$5)*'Daily Sales'!$D$6:$D$371) -> 0 | L9: =SUMPRODUCT((MONTH('Daily Sales'!$B$6:$B$371)=10)*(YEAR('Daily Sales'!$B$6:$B$371)=$C$5)*'Daily Sales'!$D$6:$D$371) -> 0 | M9: =SUMPRODUCT((MONTH('Daily Sales'!$B$6:$B$371)=11)*(YEAR('Daily Sales'!$B$6:$B$371)=$C$5)*'Daily Sales'!$D$6:$D$371) -> 0 | N9: =SUMPRODUCT((MONTH('Daily Sales'!$B$6:$B$371)=12)*(YEAR('Daily Sales'!$B$6:$B$371)=$C$5)*'Daily Sales'!$D$6:$D$371) -> 0 | O9: =SUM(C9:N9) -> 7200.99
B10: Square cash sales | C10: =SUMPRODUCT((MONTH('Daily Sales'!$B$6:$B$371)=1)*(YEAR('Daily Sales'!$B$6:$B$371)=$C$5)*'Daily Sales'!$E$6:$E$371) -> 17.73 | D10: =SUMPRODUCT((MONTH('Daily Sales'!$B$6:$B$371)=2)*(YEAR('Daily Sales'!$B$6:$B$371)=$C$5)*'Daily Sales'!$E$6:$E$371) -> 20.12 | E10: =SUMPRODUCT((MONTH('Daily Sales'!$B$6:$B$371)=3)*(YEAR('Daily Sales'!$B$6:$B$371)=$C$5)*'Daily Sales'!$E$6:$E$371) -> 31.77 | F10: =SUMPRODUCT((MONTH('Daily Sales'!$B$6:$B$371)=4)*(YEAR('Daily Sales'!$B$6:$B$371)=$C$5)*'Daily Sales'!$E$6:$E$371) -> 0 | G10: =SUMPRODUCT((MONTH('Daily Sales'!$B$6:$B$371)=5)*(YEAR('Daily Sales'!$B$6:$B$371)=$C$5)*'Daily Sales'!$E$6:$E$371) -> 0 | H10: =SUMPRODUCT((MONTH('Daily Sales'!$B$6:$B$371)=6)*(YEAR('Daily Sales'!$B$6:$B$371)=$C$5)*'Daily Sales'!$E$6:$E$371) -> 0 | I10: =SUMPRODUCT((MONTH('Daily Sales'!$B$6:$B$371)=7)*(YEAR('Daily Sales'!$B$6:$B$371)=$C$5)*'Daily Sales'!$E$6:$E$371) -> 0 | J10: =SUMPRODUCT((MONTH('Daily Sales'!$B$6:$B$371)=8)*(YEAR('Daily Sales'!$B$6:$B$371)=$C$5)*'Daily Sales'!$E$6:$E$371) -> 0 | K10: =SUMPRODUCT((MONTH('Daily Sales'!$B$6:$B$371)=9)*(YEAR('Daily Sales'!$B$6:$B$371)=$C$5)*'Daily Sales'!$E$6:$E$371) -> 0 | L10: =SUMPRODUCT((MONTH('Daily Sales'!$B$6:$B$371)=10)*(YEAR('Daily Sales'!$B$6:$B$371)=$C$5)*'Daily Sales'!$E$6:$E$371) -> 0 | M10: =SUMPRODUCT((MONTH('Daily Sales'!$B$6:$B$371)=11)*(YEAR('Daily Sales'!$B$6:$B$371)=$C$5)*'Daily Sales'!$E$6:$E$371) -> 0 | N10: =SUMPRODUCT((MONTH('Daily Sales'!$B$6:$B$371)=12)*(YEAR('Daily Sales'!$B$6:$B$371)=$C$5)*'Daily Sales'!$E$6:$E$371) -> 0 | O10: =SUM(C10:N10) -> 69.62
B11: Own cash sales | C11: =SUMPRODUCT((MONTH('Daily Sales'!$B$6:$B$371)=1)*(YEAR('Daily Sales'!$B$6:$B$371)=$C$5)*IF('Daily Sales'!$G$6:$G$371>0,'Daily Sales'!$G$6:$G$371,'Daily Sales'!$F$6:$F$371)) -> 0 | D11: =SUMPRODUCT((MONTH('Daily Sales'!$B$6:$B$371)=2)*(YEAR('Daily Sales'!$B$6:$B$371)=$C$5)*IF('Daily Sales'!$G$6:$G$371>0,'Daily Sales'!$G$6:$G$371,'Daily Sales'!$F$6:$F$371)) -> 0 | E11: =SUMPRODUCT((MONTH('Daily Sales'!$B$6:$B$371)=3)*(YEAR('Daily Sales'!$B$6:$B$371)=$C$5)*IF('Daily Sales'!$G$6:$G$371>0,'Daily Sales'!$G$6:$G$371,'Daily Sales'!$F$6:$F$371)) -> 0 | F11: =SUMPRODUCT((MONTH('Daily Sales'!$B$6:$B$371)=4)*(YEAR('Daily Sales'!$B$6:$B$371)=$C$5)*IF('Daily Sales'!$G$6:$G$371>0,'Daily Sales'!$G$6:$G$371,'Daily Sales'!$F$6:$F$371)) -> 0 | G11: =SUMPRODUCT((MONTH('Daily Sales'!$B$6:$B$371)=5)*(YEAR('Daily Sales'!$B$6:$B$371)=$C$5)*IF('Daily Sales'!$G$6:$G$371>0,'Daily Sales'!$G$6:$G$371,'Daily Sales'!$F$6:$F$371)) -> 0 | H11: =SUMPRODUCT((MONTH('Daily Sales'!$B$6:$B$371)=6)*(YEAR('Daily Sales'!$B$6:$B$371)=$C$5)*IF('Daily Sales'!$G$6:$G$371>0,'Daily Sales'!$G$6:$G$371,'Daily Sales'!$F$6:$F$371)) -> 0 | I11: =SUMPRODUCT((MONTH('Daily Sales'!$B$6:$B$371)=7)*(YEAR('Daily Sales'!$B$6:$B$371)=$C$5)*IF('Daily Sales'!$G$6:$G$371>0,'Daily Sales'!$G$6:$G$371,'Daily Sales'!$F$6:$F$371)) -> 0 | J11: =SUMPRODUCT((MONTH('Daily Sales'!$B$6:$B$371)=8)*(YEAR('Daily Sales'!$B$6:$B$371)=$C$5)*IF('Daily Sales'!$G$6:$G$371>0,'Daily Sales'!$G$6:$G$371,'Daily Sales'!$F$6:$F$371)) -> 0 | K11: =SUMPRODUCT((MONTH('Daily Sales'!$B$6:$B$371)=9)*(YEAR('Daily Sales'!$B$6:$B$371)=$C$5)*IF('Daily Sales'!$G$6:$G$371>0,'Daily Sales'!$G$6:$G$371,'Daily Sales'!$F$6:$F$371)) -> 0 | L11: =SUMPRODUCT((MONTH('Daily Sales'!$B$6:$B$371)=10)*(YEAR('Daily Sales'!$B$6:$B$371)=$C$5)*IF('Daily Sales'!$G$6:$G$371>0,'Daily Sales'!$G$6:$G$371,'Daily Sales'!$F$6:$F$371)) -> 0 | M11: =SUMPRODUCT((MONTH('Daily Sales'!$B$6:$B$371)=11)*(YEAR('Daily Sales'!$B$6:$B$371)=$C$5)*IF('Daily Sales'!$G$6:$G$371>0,'Daily Sales'!$G$6:$G$371,'Daily Sales'!$F$6:$F$371)) -> 0 | N11: =SUMPRODUCT((MONTH('Daily Sales'!$B$6:$B$371)=12)*(YEAR('Daily Sales'!$B$6:$B$371)=$C$5)*IF('Daily Sales'!$G$6:$G$371>0,'Daily Sales'!$G$6:$G$371,'Daily Sales'!$F$6:$F$371)) -> 0 | O11: =SUM(C11:N11) -> 0
B12: TOTAL REVENUE | C12: =C9+C10+C11 -> 1807.53 | D12: =D9+D10+D11 -> 1732.82 | E12: =E9+E10+E11 -> 2437.21 | F12: =F9+F10+F11 -> 1293.05 | G12: =G9+G10+G11 -> 0 | H12: =H9+H10+H11 -> 0 | I12: =I9+I10+I11 -> 0 | J12: =J9+J10+J11 -> 0 | ... N12: =N9+N10+N11 -> 0 | O12: =SUM(C12:N12) -> 7270.61
B14: COST OF GOODS SOLD
B15: Stock — coffee | C15: =SUMPRODUCT((MONTH(Expenses!$B$6:$B$500)=1)*(YEAR(Expenses!$B$6:$B$500)=$C$5)*(Expenses!$C$6:$C$500="Stock — coffee")*Expenses!$E$6:$E$500) -> 38 | D15: =SUMPRODUCT((MONTH(Expenses!$B$6:$B$500)=2)*(YEAR(Expenses!$B$6:$B$500)=$C$5)*(Expenses!$C$6:$C$500="Stock — coffee")*Expenses!$E$6:$E$500) -> 114 | E15: =SUMPRODUCT((MONTH(Expenses!$B$6:$B$500)=3)*(YEAR(Expenses!$B$6:$B$500)=$C$5)*(Expenses!$C$6:$C$500="Stock — coffee")*Expenses!$E$6:$E$500) -> 76 | F15: =SUMPRODUCT((MONTH(Expenses!$B$6:$B$500)=4)*(YEAR(Expenses!$B$6:$B$500)=$C$5)*(Expenses!$C$6:$C$500="Stock — coffee")*Expenses!$E$6:$E$500) -> 0 | G15: =SUMPRODUCT((MONTH(Expenses!$B$6:$B$500)=5)*(YEAR(Expenses!$B$6:$B$500)=$C$5)*(Expenses!$C$6:$C$500="Stock — coffee")*Expenses!$E$6:$E$500) -> 0 | H15: =SUMPRODUCT((MONTH(Expenses!$B$6:$B$500)=6)*(YEAR(Expenses!$B$6:$B$500)=$C$5)*(Expenses!$C$6:$C$500="Stock — coffee")*Expenses!$E$6:$E$500) -> 0 | I15: =SUMPRODUCT((MONTH(Expenses!$B$6:$B$500)=7)*(YEAR(Expenses!$B$6:$B$500)=$C$5)*(Expenses!$C$6:$C$500="Stock — coffee")*Expenses!$E$6:$E$500) -> 0 | J15: =SUMPRODUCT((MONTH(Expenses!$B$6:$B$500)=8)*(YEAR(Expenses!$B$6:$B$500)=$C$5)*(Expenses!$C$6:$C$500="Stock — coffee")*Expenses!$E$6:$E$500) -> 0 | K15: =SUMPRODUCT((MONTH(Expenses!$B$6:$B$500)=9)*(YEAR(Expenses!$B$6:$B$500)=$C$5)*(Expenses!$C$6:$C$500="Stock — coffee")*Expenses!$E$6:$E$500) -> 0 | L15: =SUMPRODUCT((MONTH(Expenses!$B$6:$B$500)=10)*(YEAR(Expenses!$B$6:$B$500)=$C$5)*(Expenses!$C$6:$C$500="Stock — coffee")*Expenses!$E$6:$E$500) -> 0 | M15: =SUMPRODUCT((MONTH(Expenses!$B$6:$B$500)=11)*(YEAR(Expenses!$B$6:$B$500)=$C$5)*(Expenses!$C$6:$C$500="Stock — coffee")*Expenses!$E$6:$E$500) -> 0 | N15: =SUMPRODUCT((MONTH(Expenses!$B$6:$B$500)=12)*(YEAR(Expenses!$B$6:$B$500)=$C$5)*(Expenses!$C$6:$C$500="Stock — coffee")*Expenses!$E$6:$E$500) -> 0 | O15: =SUM(C15:N15) -> 228
B16: Stock — dairy | C16: =SUMPRODUCT((MONTH(Expenses!$B$6:$B$500)=1)*(YEAR(Expenses!$B$6:$B$500)=$C$5)*(Expenses!$C$6:$C$500="Stock — dairy")*Expenses!$E$6:$E$500) -> 0 | D16: =SUMPRODUCT((MONTH(Expenses!$B$6:$B$500)=2)*(YEAR(Expenses!$B$6:$B$500)=$C$5)*(Expenses!$C$6:$C$500="Stock — dairy")*Expenses!$E$6:$E$500) -> 0 | E16: =SUMPRODUCT((MONTH(Expenses!$B$6:$B$500)=3)*(YEAR(Expenses!$B$6:$B$500)=$C$5)*(Expenses!$C$6:$C$500="Stock — dairy")*Expenses!$E$6:$E$500) -> 0 | F16: =SUMPRODUCT((MONTH(Expenses!$B$6:$B$500)=4)*(YEAR(Expenses!$B$6:$B$500)=$C$5)*(Expenses!$C$6:$C$500="Stock — dairy")*Expenses!$E$6:$E$500) -> 0 | G16: =SUMPRODUCT((MONTH(Expenses!$B$6:$B$500)=5)*(YEAR(Expenses!$B$6:$B$500)=$C$5)*(Expenses!$C$6:$C$500="Stock — dairy")*Expenses!$E$6:$E$500) -> 0 | H16: =SUMPRODUCT((MONTH(Expenses!$B$6:$B$500)=6)*(YEAR(Expenses!$B$6:$B$500)=$C$5)*(Expenses!$C$6:$C$500="Stock — dairy")*Expenses!$E$6:$E$500) -> 0 | I16: =SUMPRODUCT((MONTH(Expenses!$B$6:$B$500)=7)*(YEAR(Expenses!$B$6:$B$500)=$C$5)*(Expenses!$C$6:$C$500="Stock — dairy")*Expenses!$E$6:$E$500) -> 0 | J16: =SUMPRODUCT((MONTH(Expenses!$B$6:$B$500)=8)*(YEAR(Expenses!$B$6:$B$500)=$C$5)*(Expenses!$C$6:$C$500="Stock — dairy")*Expenses!$E$6:$E$500) -> 0 | K16: =SUMPRODUCT((MONTH(Expenses!$B$6:$B$500)=9)*(YEAR(Expenses!$B$6:$B$500)=$C$5)*(Expenses!$C$6:$C$500="Stock — dairy")*Expenses!$E$6:$E$500) -> 0 | L16: =SUMPRODUCT((MONTH(Expenses!$B$6:$B$500)=10)*(YEAR(Expenses!$B$6:$B$500)=$C$5)*(Expenses!$C$6:$C$500="Stock — dairy")*Expenses!$E$6:$E$500) -> 0 | M16: =SUMPRODUCT((MONTH(Expenses!$B$6:$B$500)=11)*(YEAR(Expenses!$B$6:$B$500)=$C$5)*(Expenses!$C$6:$C$500="Stock — dairy")*Expenses!$E$6:$E$500) -> 0 | N16: =SUMPRODUCT((MONTH(Expenses!$B$6:$B$500)=12)*(YEAR(Expenses!$B$6:$B$500)=$C$5)*(Expenses!$C$6:$C$500="Stock — dairy")*Expenses!$E$6:$E$500) -> 0 | O16: =SUM(C16:N16) -> 0
B17: Stock — syrups | C17: =SUMPRODUCT((MONTH(Expenses!$B$6:$B$500)=1)*(YEAR(Expenses!$B$6:$B$500)=$C$5)*(Expenses!$C$6:$C$500="Stock — syrups")*Expenses!$E$6:$E$500) -> 0 | D17: =SUMPRODUCT((MONTH(Expenses!$B$6:$B$500)=2)*(YEAR(Expenses!$B$6:$B$500)=$C$5)*(Expenses!$C$6:$C$500="Stock — syrups")*Expenses!$E$6:$E$500) -> 0 | E17: =SUMPRODUCT((MONTH(Expenses!$B$6:$B$500)=3)*(YEAR(Expenses!$B$6:$B$500)=$C$5)*(Expenses!$C$6:$C$500="Stock — syrups")*Expenses!$E$6:$E$500) -> 0 | F17: =SUMPRODUCT((MONTH(Expenses!$B$6:$B$500)=4)*(YEAR(Expenses!$B$6:$B$500)=$C$5)*(Expenses!$C$6:$C$500="Stock — syrups")*Expenses!$E$6:$E$500) -> 0 | G17: =SUMPRODUCT((MONTH(Expenses!$B$6:$B$500)=5)*(YEAR(Expenses!$B$6:$B$500)=$C$5)*(Expenses!$C$6:$C$500="Stock — syrups")*Expenses!$E$6:$E$500) -> 0 | H17: =SUMPRODUCT((MONTH(Expenses!$B$6:$B$500)=6)*(YEAR(Expenses!$B$6:$B$500)=$C$5)*(Expenses!$C$6:$C$500="Stock — syrups")*Expenses!$E$6:$E$500) -> 0 | I17: =SUMPRODUCT((MONTH(Expenses!$B$6:$B$500)=7)*(YEAR(Expenses!$B$6:$B$500)=$C$5)*(Expenses!$C$6:$C$500="Stock — syrups")*Expenses!$E$6:$E$500) -> 0 | J17: =SUMPRODUCT((MONTH(Expenses!$B$6:$B$500)=8)*(YEAR(Expenses!$B$6:$B$500)=$C$5)*(Expenses!$C$6:$C$500="Stock — syrups")*Expenses!$E$6:$E$500) -> 0 | K17: =SUMPRODUCT((MONTH(Expenses!$B$6:$B$500)=9)*(YEAR(Expenses!$B$6:$B$500)=$C$5)*(Expenses!$C$6:$C$500="Stock — syrups")*Expenses!$E$6:$E$500) -> 0 | L17: =SUMPRODUCT((MONTH(Expenses!$B$6:$B$500)=10)*(YEAR(Expenses!$B$6:$B$500)=$C$5)*(Expenses!$C$6:$C$500="Stock — syrups")*Expenses!$E$6:$E$500) -> 0 | M17: =SUMPRODUCT((MONTH(Expenses!$B$6:$B$500)=11)*(YEAR(Expenses!$B$6:$B$500)=$C$5)*(Expenses!$C$6:$C$500="Stock — syrups")*Expenses!$E$6:$E$500) -> 0 | N17: =SUMPRODUCT((MONTH(Expenses!$B$6:$B$500)=12)*(YEAR(Expenses!$B$6:$B$500)=$C$5)*(Expenses!$C$6:$C$500="Stock — syrups")*Expenses!$E$6:$E$500) -> 0 | O17: =SUM(C17:N17) -> 0
B18: Stock — cakes | C18: =SUMPRODUCT((MONTH(Expenses!$B$6:$B$500)=1)*(YEAR(Expenses!$B$6:$B$500)=$C$5)*(Expenses!$C$6:$C$500="Stock — cakes")*Expenses!$E$6:$E$500) -> 0 | D18: =SUMPRODUCT((MONTH(Expenses!$B$6:$B$500)=2)*(YEAR(Expenses!$B$6:$B$500)=$C$5)*(Expenses!$C$6:$C$500="Stock — cakes")*Expenses!$E$6:$E$500) -> 0 | E18: =SUMPRODUCT((MONTH(Expenses!$B$6:$B$500)=3)*(YEAR(Expenses!$B$6:$B$500)=$C$5)*(Expenses!$C$6:$C$500="Stock — cakes")*Expenses!$E$6:$E$500) -> 0 | F18: =SUMPRODUCT((MONTH(Expenses!$B$6:$B$500)=4)*(YEAR(Expenses!$B$6:$B$500)=$C$5)*(Expenses!$C$6:$C$500="Stock — cakes")*Expenses!$E$6:$E$500) -> 0 | G18: =SUMPRODUCT((MONTH(Expenses!$B$6:$B$500)=5)*(YEAR(Expenses!$B$6:$B$500)=$C$5)*(Expenses!$C$6:$C$500="Stock — cakes")*Expenses!$E$6:$E$500) -> 0 | H18: =SUMPRODUCT((MONTH(Expenses!$B$6:$B$500)=6)*(YEAR(Expenses!$B$6:$B$500)=$C$5)*(Expenses!$C$6:$C$500="Stock — cakes")*Expenses!$E$6:$E$500) -> 0 | I18: =SUMPRODUCT((MONTH(Expenses!$B$6:$B$500)=7)*(YEAR(Expenses!$B$6:$B$500)=$C$5)*(Expenses!$C$6:$C$500="Stock — cakes")*Expenses!$E$6:$E$500) -> 0 | J18: =SUMPRODUCT((MONTH(Expenses!$B$6:$B$500)=8)*(YEAR(Expenses!$B$6:$B$500)=$C$5)*(Expenses!$C$6:$C$500="Stock — cakes")*Expenses!$E$6:$E$500) -> 0 | K18: =SUMPRODUCT((MONTH(Expenses!$B$6:$B$500)=9)*(YEAR(Expenses!$B$6:$B$500)=$C$5)*(Expenses!$C$6:$C$500="Stock — cakes")*Expenses!$E$6:$E$500) -> 0 | L18: =SUMPRODUCT((MONTH(Expenses!$B$6:$B$500)=10)*(YEAR(Expenses!$B$6:$B$500)=$C$5)*(Expenses!$C$6:$C$500="Stock — cakes")*Expenses!$E$6:$E$500) -> 0 | M18: =SUMPRODUCT((MONTH(Expenses!$B$6:$B$500)=11)*(YEAR(Expenses!$B$6:$B$500)=$C$5)*(Expenses!$C$6:$C$500="Stock — cakes")*Expenses!$E$6:$E$500) -> 0 | N18: =SUMPRODUCT((MONTH(Expenses!$B$6:$B$500)=12)*(YEAR(Expenses!$B$6:$B$500)=$C$5)*(Expenses!$C$6:$C$500="Stock — cakes")*Expenses!$E$6:$E$500) -> 0 | O18: =SUM(C18:N18) -> 0
B19: Stock — food | C19: =SUMPRODUCT((MONTH(Expenses!$B$6:$B$500)=1)*(YEAR(Expenses!$B$6:$B$500)=$C$5)*(Expenses!$C$6:$C$500="Stock — food")*Expenses!$E$6:$E$500) -> 462.16 | D19: =SUMPRODUCT((MONTH(Expenses!$B$6:$B$500)=2)*(YEAR(Expenses!$B$6:$B$500)=$C$5)*(Expenses!$C$6:$C$500="Stock — food")*Expenses!$E$6:$E$500) -> 375.18 | E19: =SUMPRODUCT((MONTH(Expenses!$B$6:$B$500)=3)*(YEAR(Expenses!$B$6:$B$500)=$C$5)*(Expenses!$C$6:$C$500="Stock — food")*Expenses!$E$6:$E$500) -> 410.48 | F19: =SUMPRODUCT((MONTH(Expenses!$B$6:$B$500)=4)*(YEAR(Expenses!$B$6:$B$500)=$C$5)*(Expenses!$C$6:$C$500="Stock — food")*Expenses!$E$6:$E$500) -> 0 | G19: =SUMPRODUCT((MONTH(Expenses!$B$6:$B$500)=5)*(YEAR(Expenses!$B$6:$B$500)=$C$5)*(Expenses!$C$6:$C$500="Stock — food")*Expenses!$E$6:$E$500) -> 0 | H19: =SUMPRODUCT((MONTH(Expenses!$B$6:$B$500)=6)*(YEAR(Expenses!$B$6:$B$500)=$C$5)*(Expenses!$C$6:$C$500="Stock — food")*Expenses!$E$6:$E$500) -> 0 | I19: =SUMPRODUCT((MONTH(Expenses!$B$6:$B$500)=7)*(YEAR(Expenses!$B$6:$B$500)=$C$5)*(Expenses!$C$6:$C$500="Stock — food")*Expenses!$E$6:$E$500) -> 0 | J19: =SUMPRODUCT((MONTH(Expenses!$B$6:$B$500)=8)*(YEAR(Expenses!$B$6:$B$500)=$C$5)*(Expenses!$C$6:$C$500="Stock — food")*Expenses!$E$6:$E$500) -> 0 | K19: =SUMPRODUCT((MONTH(Expenses!$B$6:$B$500)=9)*(YEAR(Expenses!$B$6:$B$500)=$C$5)*(Expenses!$C$6:$C$500="Stock — food")*Expenses!$E$6:$E$500) -> 0 | L19: =SUMPRODUCT((MONTH(Expenses!$B$6:$B$500)=10)*(YEAR(Expenses!$B$6:$B$500)=$C$5)*(Expenses!$C$6:$C$500="Stock — food")*Expenses!$E$6:$E$500) -> 0 | M19: =SUMPRODUCT((MONTH(Expenses!$B$6:$B$500)=11)*(YEAR(Expenses!$B$6:$B$500)=$C$5)*(Expenses!$C$6:$C$500="Stock — food")*Expenses!$E$6:$E$500) -> 0 | N19: =SUMPRODUCT((MONTH(Expenses!$B$6:$B$500)=12)*(YEAR(Expenses!$B$6:$B$500)=$C$5)*(Expenses!$C$6:$C$500="Stock — food")*Expenses!$E$6:$E$500) -> 0 | O19: =SUM(C19:N19) -> 1247.82
B20: Stock — packaging | C20: =SUMPRODUCT((MONTH(Expenses!$B$6:$B$500)=1)*(YEAR(Expenses!$B$6:$B$500)=$C$5)*(Expenses!$C$6:$C$500="Stock — packaging")*Expenses!$E$6:$E$500) -> 0 | D20: =SUMPRODUCT((MONTH(Expenses!$B$6:$B$500)=2)*(YEAR(Expenses!$B$6:$B$500)=$C$5)*(Expenses!$C$6:$C$500="Stock — packaging")*Expenses!$E$6:$E$500) -> 0 | E20: =SUMPRODUCT((MONTH(Expenses!$B$6:$B$500)=3)*(YEAR(Expenses!$B$6:$B$500)=$C$5)*(Expenses!$C$6:$C$500="Stock — packaging")*Expenses!$E$6:$E$500) -> 0 | F20: =SUMPRODUCT((MONTH(Expenses!$B$6:$B$500)=4)*(YEAR(Expenses!$B$6:$B$500)=$C$5)*(Expenses!$C$6:$C$500="Stock — packaging")*Expenses!$E$6:$E$500) -> 0 | G20: =SUMPRODUCT((MONTH(Expenses!$B$6:$B$500)=5)*(YEAR(Expenses!$B$6:$B$500)=$C$5)*(Expenses!$C$6:$C$500="Stock — packaging")*Expenses!$E$6:$E$500) -> 0 | H20: =SUMPRODUCT((MONTH(Expenses!$B$6:$B$500)=6)*(YEAR(Expenses!$B$6:$B$500)=$C$5)*(Expenses!$C$6:$C$500="Stock — packaging")*Expenses!$E$6:$E$500) -> 0 | I20: =SUMPRODUCT((MONTH(Expenses!$B$6:$B$500)=7)*(YEAR(Expenses!$B$6:$B$500)=$C$5)*(Expenses!$C$6:$C$500="Stock — packaging")*Expenses!$E$6:$E$500) -> 0 | J20: =SUMPRODUCT((MONTH(Expenses!$B$6:$B$500)=8)*(YEAR(Expenses!$B$6:$B$500)=$C$5)*(Expenses!$C$6:$C$500="Stock — packaging")*Expenses!$E$6:$E$500) -> 0 | K20: =SUMPRODUCT((MONTH(Expenses!$B$6:$B$500)=9)*(YEAR(Expenses!$B$6:$B$500)=$C$5)*(Expenses!$C$6:$C$500="Stock — packaging")*Expenses!$E$6:$E$500) -> 0 | L20: =SUMPRODUCT((MONTH(Expenses!$B$6:$B$500)=10)*(YEAR(Expenses!$B$6:$B$500)=$C$5)*(Expenses!$C$6:$C$500="Stock — packaging")*Expenses!$E$6:$E$500) -> 0 | M20: =SUMPRODUCT((MONTH(Expenses!$B$6:$B$500)=11)*(YEAR(Expenses!$B$6:$B$500)=$C$5)*(Expenses!$C$6:$C$500="Stock — packaging")*Expenses!$E$6:$E$500) -> 0 | N20: =SUMPRODUCT((MONTH(Expenses!$B$6:$B$500)=12)*(YEAR(Expenses!$B$6:$B$500)=$C$5)*(Expenses!$C$6:$C$500="Stock — packaging")*Expenses!$E$6:$E$500) -> 0 | O20: =SUM(C20:N20) -> 0
B21: Stock — other | C21: =SUMPRODUCT((MONTH(Expenses!$B$6:$B$500)=1)*(YEAR(Expenses!$B$6:$B$500)=$C$5)*(Expenses!$C$6:$C$500="Stock — other")*Expenses!$E$6:$E$500) -> 560.17 | D21: =SUMPRODUCT((MONTH(Expenses!$B$6:$B$500)=2)*(YEAR(Expenses!$B$6:$B$500)=$C$5)*(Expenses!$C$6:$C$500="Stock — other")*Expenses!$E$6:$E$500) -> 309.16 | E21: =SUMPRODUCT((MONTH(Expenses!$B$6:$B$500)=3)*(YEAR(Expenses!$B$6:$B$500)=$C$5)*(Expenses!$C$6:$C$500="Stock — other")*Expenses!$E$6:$E$500) -> 393.07 | F21: =SUMPRODUCT((MONTH(Expenses!$B$6:$B$500)=4)*(YEAR(Expenses!$B$6:$B$500)=$C$5)*(Expenses!$C$6:$C$500="Stock — other")*Expenses!$E$6:$E$500) -> 0 | G21: =SUMPRODUCT((MONTH(Expenses!$B$6:$B$500)=5)*(YEAR(Expenses!$B$6:$B$500)=$C$5)*(Expenses!$C$6:$C$500="Stock — other")*Expenses!$E$6:$E$500) -> 0 | H21: =SUMPRODUCT((MONTH(Expenses!$B$6:$B$500)=6)*(YEAR(Expenses!$B$6:$B$500)=$C$5)*(Expenses!$C$6:$C$500="Stock — other")*Expenses!$E$6:$E$500) -> 0 | I21: =SUMPRODUCT((MONTH(Expenses!$B$6:$B$500)=7)*(YEAR(Expenses!$B$6:$B$500)=$C$5)*(Expenses!$C$6:$C$500="Stock — other")*Expenses!$E$6:$E$500) -> 0 | J21: =SUMPRODUCT((MONTH(Expenses!$B$6:$B$500)=8)*(YEAR(Expenses!$B$6:$B$500)=$C$5)*(Expenses!$C$6:$C$500="Stock — other")*Expenses!$E$6:$E$500) -> 0 | K21: =SUMPRODUCT((MONTH(Expenses!$B$6:$B$500)=9)*(YEAR(Expenses!$B$6:$B$500)=$C$5)*(Expenses!$C$6:$C$500="Stock — other")*Expenses!$E$6:$E$500) -> 0 | L21: =SUMPRODUCT((MONTH(Expenses!$B$6:$B$500)=10)*(YEAR(Expenses!$B$6:$B$500)=$C$5)*(Expenses!$C$6:$C$500="Stock — other")*Expenses!$E$6:$E$500) -> 0 | M21: =SUMPRODUCT((MONTH(Expenses!$B$6:$B$500)=11)*(YEAR(Expenses!$B$6:$B$500)=$C$5)*(Expenses!$C$6:$C$500="Stock — other")*Expenses!$E$6:$E$500) -> 0 | N21: =SUMPRODUCT((MONTH(Expenses!$B$6:$B$500)=12)*(YEAR(Expenses!$B$6:$B$500)=$C$5)*(Expenses!$C$6:$C$500="Stock — other")*Expenses!$E$6:$E$500) -> 0 | O21: =SUM(C21:N21) -> 1262.4
B22: TOTAL COGS | C22: =SUM(C15:C21) -> 1060.33 | D22: =SUM(D15:D21) -> 798.34 | E22: =SUM(E15:E21) -> 879.55 | F22: =SUM(F15:F21) -> 0 | G22: =SUM(G15:G21) -> 0 | H22: =SUM(H15:H21) -> 0 | I22: =SUM(I15:I21) -> 0 | J22: =SUM(J15:J21) -> 0 | ... N22: =SUM(N15:N21) -> 0 | O22: =SUM(C22:N22) -> 2738.22
B24: GROSS PROFIT | C24: =C12-C22 -> 747.2 | D24: =D12-D22 -> 934.48 | E24: =E12-E22 -> 1557.66 | F24: =F12-F22 -> 1293.05 | G24: =G12-G22 -> 0 | H24: =H12-H22 -> 0 | I24: =I12-I22 -> 0 | J24: =J12-J22 -> 0 | ... N24: =N12-N22 -> 0 | O24: =SUM(C24:N24) -> 4532.39
B25: Gross margin % | C25: =IFERROR(C24/C12,0) -> 0.4133818 | D25: =IFERROR(D24/D12,0) -> 0.53928279 | E25: =IFERROR(E24/E12,0) -> 0.63911604 | F25: =IFERROR(F24/F12,0) -> 1 | G25: =IFERROR(G24/G12,0) -> 0 | H25: =IFERROR(H24/H12,0) -> 0 | I25: =IFERROR(I24/I12,0) -> 0 | J25: =IFERROR(J24/J12,0) -> 0 | ... N25: =IFERROR(N24/N12,0) -> 0 | O25: =IFERROR(AVERAGE(C25:N25),0) -> 0.21598172
B27: OPERATING EXPENSES
B28: Rent | C28: =SUMPRODUCT((MONTH(Expenses!$B$6:$B$500)=1)*(YEAR(Expenses!$B$6:$B$500)=$C$5)*(Expenses!$C$6:$C$500="Rent")*Expenses!$E$6:$E$500) -> 625 | D28: =SUMPRODUCT((MONTH(Expenses!$B$6:$B$500)=2)*(YEAR(Expenses!$B$6:$B$500)=$C$5)*(Expenses!$C$6:$C$500="Rent")*Expenses!$E$6:$E$500) -> 625 | E28: =SUMPRODUCT((MONTH(Expenses!$B$6:$B$500)=3)*(YEAR(Expenses!$B$6:$B$500)=$C$5)*(Expenses!$C$6:$C$500="Rent")*Expenses!$E$6:$E$500) -> 625 | F28: =SUMPRODUCT((MONTH(Expenses!$B$6:$B$500)=4)*(YEAR(Expenses!$B$6:$B$500)=$C$5)*(Expenses!$C$6:$C$500="Rent")*Expenses!$E$6:$E$500) -> 0 | G28: =SUMPRODUCT((MONTH(Expenses!$B$6:$B$500)=5)*(YEAR(Expenses!$B$6:$B$500)=$C$5)*(Expenses!$C$6:$C$500="Rent")*Expenses!$E$6:$E$500) -> 0 | H28: =SUMPRODUCT((MONTH(Expenses!$B$6:$B$500)=6)*(YEAR(Expenses!$B$6:$B$500)=$C$5)*(Expenses!$C$6:$C$500="Rent")*Expenses!$E$6:$E$500) -> 0 | I28: =SUMPRODUCT((MONTH(Expenses!$B$6:$B$500)=7)*(YEAR(Expenses!$B$6:$B$500)=$C$5)*(Expenses!$C$6:$C$500="Rent")*Expenses!$E$6:$E$500) -> 0 | J28: =SUMPRODUCT((MONTH(Expenses!$B$6:$B$500)=8)*(YEAR(Expenses!$B$6:$B$500)=$C$5)*(Expenses!$C$6:$C$500="Rent")*Expenses!$E$6:$E$500) -> 0 | K28: =SUMPRODUCT((MONTH(Expenses!$B$6:$B$500)=9)*(YEAR(Expenses!$B$6:$B$500)=$C$5)*(Expenses!$C$6:$C$500="Rent")*Expenses!$E$6:$E$500) -> 0 | L28: =SUMPRODUCT((MONTH(Expenses!$B$6:$B$500)=10)*(YEAR(Expenses!$B$6:$B$500)=$C$5)*(Expenses!$C$6:$C$500="Rent")*Expenses!$E$6:$E$500) -> 0 | M28: =SUMPRODUCT((MONTH(Expenses!$B$6:$B$500)=11)*(YEAR(Expenses!$B$6:$B$500)=$C$5)*(Expenses!$C$6:$C$500="Rent")*Expenses!$E$6:$E$500) -> 0 | N28: =SUMPRODUCT((MONTH(Expenses!$B$6:$B$500)=12)*(YEAR(Expenses!$B$6:$B$500)=$C$5)*(Expenses!$C$6:$C$500="Rent")*Expenses!$E$6:$E$500) -> 0 | O28: =SUM(C28:N28) -> 1875
B29: Utilities | C29: =SUMPRODUCT((MONTH(Expenses!$B$6:$B$500)=1)*(YEAR(Expenses!$B$6:$B$500)=$C$5)*(Expenses!$C$6:$C$500="Utilities")*Expenses!$E$6:$E$500) -> 385 | D29: =SUMPRODUCT((MONTH(Expenses!$B$6:$B$500)=2)*(YEAR(Expenses!$B$6:$B$500)=$C$5)*(Expenses!$C$6:$C$500="Utilities")*Expenses!$E$6:$E$500) -> 588.68 | E29: =SUMPRODUCT((MONTH(Expenses!$B$6:$B$500)=3)*(YEAR(Expenses!$B$6:$B$500)=$C$5)*(Expenses!$C$6:$C$500="Utilities")*Expenses!$E$6:$E$500) -> 446.13 | F29: =SUMPRODUCT((MONTH(Expenses!$B$6:$B$500)=4)*(YEAR(Expenses!$B$6:$B$500)=$C$5)*(Expenses!$C$6:$C$500="Utilities")*Expenses!$E$6:$E$500) -> 0 | G29: =SUMPRODUCT((MONTH(Expenses!$B$6:$B$500)=5)*(YEAR(Expenses!$B$6:$B$500)=$C$5)*(Expenses!$C$6:$C$500="Utilities")*Expenses!$E$6:$E$500) -> 0 | H29: =SUMPRODUCT((MONTH(Expenses!$B$6:$B$500)=6)*(YEAR(Expenses!$B$6:$B$500)=$C$5)*(Expenses!$C$6:$C$500="Utilities")*Expenses!$E$6:$E$500) -> 0 | I29: =SUMPRODUCT((MONTH(Expenses!$B$6:$B$500)=7)*(YEAR(Expenses!$B$6:$B$500)=$C$5)*(Expenses!$C$6:$C$500="Utilities")*Expenses!$E$6:$E$500) -> 0 | J29: =SUMPRODUCT((MONTH(Expenses!$B$6:$B$500)=8)*(YEAR(Expenses!$B$6:$B$500)=$C$5)*(Expenses!$C$6:$C$500="Utilities")*Expenses!$E$6:$E$500) -> 0 | K29: =SUMPRODUCT((MONTH(Expenses!$B$6:$B$500)=9)*(YEAR(Expenses!$B$6:$B$500)=$C$5)*(Expenses!$C$6:$C$500="Utilities")*Expenses!$E$6:$E$500) -> 0 | L29: =SUMPRODUCT((MONTH(Expenses!$B$6:$B$500)=10)*(YEAR(Expenses!$B$6:$B$500)=$C$5)*(Expenses!$C$6:$C$500="Utilities")*Expenses!$E$6:$E$500) -> 0 | M29: =SUMPRODUCT((MONTH(Expenses!$B$6:$B$500)=11)*(YEAR(Expenses!$B$6:$B$500)=$C$5)*(Expenses!$C$6:$C$500="Utilities")*Expenses!$E$6:$E$500) -> 0 | N29: =SUMPRODUCT((MONTH(Expenses!$B$6:$B$500)=12)*(YEAR(Expenses!$B$6:$B$500)=$C$5)*(Expenses!$C$6:$C$500="Utilities")*Expenses!$E$6:$E$500) -> 0 | O29: =SUM(C29:N29) -> 1419.81
B30: Wages | C30: =SUMPRODUCT((MONTH(Expenses!$B$6:$B$500)=1)*(YEAR(Expenses!$B$6:$B$500)=$C$5)*(Expenses!$C$6:$C$500="Wages")*Expenses!$E$6:$E$500) -> 0 | D30: =SUMPRODUCT((MONTH(Expenses!$B$6:$B$500)=2)*(YEAR(Expenses!$B$6:$B$500)=$C$5)*(Expenses!$C$6:$C$500="Wages")*Expenses!$E$6:$E$500) -> 0 | E30: =SUMPRODUCT((MONTH(Expenses!$B$6:$B$500)=3)*(YEAR(Expenses!$B$6:$B$500)=$C$5)*(Expenses!$C$6:$C$500="Wages")*Expenses!$E$6:$E$500) -> 0 | F30: =SUMPRODUCT((MONTH(Expenses!$B$6:$B$500)=4)*(YEAR(Expenses!$B$6:$B$500)=$C$5)*(Expenses!$C$6:$C$500="Wages")*Expenses!$E$6:$E$500) -> 0 | G30: =SUMPRODUCT((MONTH(Expenses!$B$6:$B$500)=5)*(YEAR(Expenses!$B$6:$B$500)=$C$5)*(Expenses!$C$6:$C$500="Wages")*Expenses!$E$6:$E$500) -> 0 | H30: =SUMPRODUCT((MONTH(Expenses!$B$6:$B$500)=6)*(YEAR(Expenses!$B$6:$B$500)=$C$5)*(Expenses!$C$6:$C$500="Wages")*Expenses!$E$6:$E$500) -> 0 | I30: =SUMPRODUCT((MONTH(Expenses!$B$6:$B$500)=7)*(YEAR(Expenses!$B$6:$B$500)=$C$5)*(Expenses!$C$6:$C$500="Wages")*Expenses!$E$6:$E$500) -> 0 | J30: =SUMPRODUCT((MONTH(Expenses!$B$6:$B$500)=8)*(YEAR(Expenses!$B$6:$B$500)=$C$5)*(Expenses!$C$6:$C$500="Wages")*Expenses!$E$6:$E$500) -> 0 | K30: =SUMPRODUCT((MONTH(Expenses!$B$6:$B$500)=9)*(YEAR(Expenses!$B$6:$B$500)=$C$5)*(Expenses!$C$6:$C$500="Wages")*Expenses!$E$6:$E$500) -> 0 | L30: =SUMPRODUCT((MONTH(Expenses!$B$6:$B$500)=10)*(YEAR(Expenses!$B$6:$B$500)=$C$5)*(Expenses!$C$6:$C$500="Wages")*Expenses!$E$6:$E$500) -> 0 | M30: =SUMPRODUCT((MONTH(Expenses!$B$6:$B$500)=11)*(YEAR(Expenses!$B$6:$B$500)=$C$5)*(Expenses!$C$6:$C$500="Wages")*Expenses!$E$6:$E$500) -> 0 | N30: =SUMPRODUCT((MONTH(Expenses!$B$6:$B$500)=12)*(YEAR(Expenses!$B$6:$B$500)=$C$5)*(Expenses!$C$6:$C$500="Wages")*Expenses!$E$6:$E$500) -> 0 | O30: =SUM(C30:N30) -> 0
B31: Marketing | C31: =SUMPRODUCT((MONTH(Expenses!$B$6:$B$500)=1)*(YEAR(Expenses!$B$6:$B$500)=$C$5)*(Expenses!$C$6:$C$500="Marketing")*Expenses!$E$6:$E$500) -> 0 | D31: =SUMPRODUCT((MONTH(Expenses!$B$6:$B$500)=2)*(YEAR(Expenses!$B$6:$B$500)=$C$5)*(Expenses!$C$6:$C$500="Marketing")*Expenses!$E$6:$E$500) -> 0 | E31: =SUMPRODUCT((MONTH(Expenses!$B$6:$B$500)=3)*(YEAR(Expenses!$B$6:$B$500)=$C$5)*(Expenses!$C$6:$C$500="Marketing")*Expenses!$E$6:$E$500) -> 0 | F31: =SUMPRODUCT((MONTH(Expenses!$B$6:$B$500)=4)*(YEAR(Expenses!$B$6:$B$500)=$C$5)*(Expenses!$C$6:$C$500="Marketing")*Expenses!$E$6:$E$500) -> 0 | G31: =SUMPRODUCT((MONTH(Expenses!$B$6:$B$500)=5)*(YEAR(Expenses!$B$6:$B$500)=$C$5)*(Expenses!$C$6:$C$500="Marketing")*Expenses!$E$6:$E$500) -> 0 | H31: =SUMPRODUCT((MONTH(Expenses!$B$6:$B$500)=6)*(YEAR(Expenses!$B$6:$B$500)=$C$5)*(Expenses!$C$6:$C$500="Marketing")*Expenses!$E$6:$E$500) -> 0 | I31: =SUMPRODUCT((MONTH(Expenses!$B$6:$B$500)=7)*(YEAR(Expenses!$B$6:$B$500)=$C$5)*(Expenses!$C$6:$C$500="Marketing")*Expenses!$E$6:$E$500) -> 0 | J31: =SUMPRODUCT((MONTH(Expenses!$B$6:$B$500)=8)*(YEAR(Expenses!$B$6:$B$500)=$C$5)*(Expenses!$C$6:$C$500="Marketing")*Expenses!$E$6:$E$500) -> 0 | K31: =SUMPRODUCT((MONTH(Expenses!$B$6:$B$500)=9)*(YEAR(Expenses!$B$6:$B$500)=$C$5)*(Expenses!$C$6:$C$500="Marketing")*Expenses!$E$6:$E$500) -> 0 | L31: =SUMPRODUCT((MONTH(Expenses!$B$6:$B$500)=10)*(YEAR(Expenses!$B$6:$B$500)=$C$5)*(Expenses!$C$6:$C$500="Marketing")*Expenses!$E$6:$E$500) -> 0 | M31: =SUMPRODUCT((MONTH(Expenses!$B$6:$B$500)=11)*(YEAR(Expenses!$B$6:$B$500)=$C$5)*(Expenses!$C$6:$C$500="Marketing")*Expenses!$E$6:$E$500) -> 0 | N31: =SUMPRODUCT((MONTH(Expenses!$B$6:$B$500)=12)*(YEAR(Expenses!$B$6:$B$500)=$C$5)*(Expenses!$C$6:$C$500="Marketing")*Expenses!$E$6:$E$500) -> 0 | O31: =SUM(C31:N31) -> 0
B32: Square fees | C32: =SUMPRODUCT((MONTH(Expenses!$B$6:$B$500)=1)*(YEAR(Expenses!$B$6:$B$500)=$C$5)*(Expenses!$C$6:$C$500="Square fees")*Expenses!$E$6:$E$500) -> 0 | D32: =SUMPRODUCT((MONTH(Expenses!$B$6:$B$500)=2)*(YEAR(Expenses!$B$6:$B$500)=$C$5)*(Expenses!$C$6:$C$500="Square fees")*Expenses!$E$6:$E$500) -> 0 | E32: =SUMPRODUCT((MONTH(Expenses!$B$6:$B$500)=3)*(YEAR(Expenses!$B$6:$B$500)=$C$5)*(Expenses!$C$6:$C$500="Square fees")*Expenses!$E$6:$E$500) -> 0 | F32: =SUMPRODUCT((MONTH(Expenses!$B$6:$B$500)=4)*(YEAR(Expenses!$B$6:$B$500)=$C$5)*(Expenses!$C$6:$C$500="Square fees")*Expenses!$E$6:$E$500) -> 0 | G32: =SUMPRODUCT((MONTH(Expenses!$B$6:$B$500)=5)*(YEAR(Expenses!$B$6:$B$500)=$C$5)*(Expenses!$C$6:$C$500="Square fees")*Expenses!$E$6:$E$500) -> 0 | H32: =SUMPRODUCT((MONTH(Expenses!$B$6:$B$500)=6)*(YEAR(Expenses!$B$6:$B$500)=$C$5)*(Expenses!$C$6:$C$500="Square fees")*Expenses!$E$6:$E$500) -> 0 | I32: =SUMPRODUCT((MONTH(Expenses!$B$6:$B$500)=7)*(YEAR(Expenses!$B$6:$B$500)=$C$5)*(Expenses!$C$6:$C$500="Square fees")*Expenses!$E$6:$E$500) -> 0 | J32: =SUMPRODUCT((MONTH(Expenses!$B$6:$B$500)=8)*(YEAR(Expenses!$B$6:$B$500)=$C$5)*(Expenses!$C$6:$C$500="Square fees")*Expenses!$E$6:$E$500) -> 0 | K32: =SUMPRODUCT((MONTH(Expenses!$B$6:$B$500)=9)*(YEAR(Expenses!$B$6:$B$500)=$C$5)*(Expenses!$C$6:$C$500="Square fees")*Expenses!$E$6:$E$500) -> 0 | L32: =SUMPRODUCT((MONTH(Expenses!$B$6:$B$500)=10)*(YEAR(Expenses!$B$6:$B$500)=$C$5)*(Expenses!$C$6:$C$500="Square fees")*Expenses!$E$6:$E$500) -> 0 | M32: =SUMPRODUCT((MONTH(Expenses!$B$6:$B$500)=11)*(YEAR(Expenses!$B$6:$B$500)=$C$5)*(Expenses!$C$6:$C$500="Square fees")*Expenses!$E$6:$E$500) -> 0 | N32: =SUMPRODUCT((MONTH(Expenses!$B$6:$B$500)=12)*(YEAR(Expenses!$B$6:$B$500)=$C$5)*(Expenses!$C$6:$C$500="Square fees")*Expenses!$E$6:$E$500) -> 0 | O32: =SUM(C32:N32) -> 0
B33: Other | C33: =SUMPRODUCT((MONTH(Expenses!$B$6:$B$500)=1)*(YEAR(Expenses!$B$6:$B$500)=$C$5)*(Expenses!$C$6:$C$500="Other")*Expenses!$E$6:$E$500) -> 20.69 | D33: =SUMPRODUCT((MONTH(Expenses!$B$6:$B$500)=2)*(YEAR(Expenses!$B$6:$B$500)=$C$5)*(Expenses!$C$6:$C$500="Other")*Expenses!$E$6:$E$500) -> 44.19 | E33: =SUMPRODUCT((MONTH(Expenses!$B$6:$B$500)=3)*(YEAR(Expenses!$B$6:$B$500)=$C$5)*(Expenses!$C$6:$C$500="Other")*Expenses!$E$6:$E$500) -> 909.42 | F33: =SUMPRODUCT((MONTH(Expenses!$B$6:$B$500)=4)*(YEAR(Expenses!$B$6:$B$500)=$C$5)*(Expenses!$C$6:$C$500="Other")*Expenses!$E$6:$E$500) -> 0 | G33: =SUMPRODUCT((MONTH(Expenses!$B$6:$B$500)=5)*(YEAR(Expenses!$B$6:$B$500)=$C$5)*(Expenses!$C$6:$C$500="Other")*Expenses!$E$6:$E$500) -> 0 | H33: =SUMPRODUCT((MONTH(Expenses!$B$6:$B$500)=6)*(YEAR(Expenses!$B$6:$B$500)=$C$5)*(Expenses!$C$6:$C$500="Other")*Expenses!$E$6:$E$500) -> 0 | I33: =SUMPRODUCT((MONTH(Expenses!$B$6:$B$500)=7)*(YEAR(Expenses!$B$6:$B$500)=$C$5)*(Expenses!$C$6:$C$500="Other")*Expenses!$E$6:$E$500) -> 0 | J33: =SUMPRODUCT((MONTH(Expenses!$B$6:$B$500)=8)*(YEAR(Expenses!$B$6:$B$500)=$C$5)*(Expenses!$C$6:$C$500="Other")*Expenses!$E$6:$E$500) -> 0 | K33: =SUMPRODUCT((MONTH(Expenses!$B$6:$B$500)=9)*(YEAR(Expenses!$B$6:$B$500)=$C$5)*(Expenses!$C$6:$C$500="Other")*Expenses!$E$6:$E$500) -> 0 | L33: =SUMPRODUCT((MONTH(Expenses!$B$6:$B$500)=10)*(YEAR(Expenses!$B$6:$B$500)=$C$5)*(Expenses!$C$6:$C$500="Other")*Expenses!$E$6:$E$500) -> 0 | M33: =SUMPRODUCT((MONTH(Expenses!$B$6:$B$500)=11)*(YEAR(Expenses!$B$6:$B$500)=$C$5)*(Expenses!$C$6:$C$500="Other")*Expenses!$E$6:$E$500) -> 0 | N33: =SUMPRODUCT((MONTH(Expenses!$B$6:$B$500)=12)*(YEAR(Expenses!$B$6:$B$500)=$C$5)*(Expenses!$C$6:$C$500="Other")*Expenses!$E$6:$E$500) -> 0 | O33: =SUM(C33:N33) -> 974.3
B34: TOTAL OPEX | C34: =SUM(C28:C33) -> 1030.69 | D34: =SUM(D28:D33) -> 1257.87 | E34: =SUM(E28:E33) -> 1980.55 | F34: =SUM(F28:F33) -> 0 | G34: =SUM(G28:G33) -> 0 | H34: =SUM(H28:H33) -> 0 | I34: =SUM(I28:I33) -> 0 | J34: =SUM(J28:J33) -> 0 | ... N34: =SUM(N28:N33) -> 0 | O34: =SUM(C34:N34) -> 4269.11
B36: NET PROFIT (before tax) | C36: =C24-C34 -> -283.49 | D36: =D24-D34 -> -323.39 | E36: =E24-E34 -> -422.89 | F36: =F24-F34 -> 1293.05 | G36: =G24-G34 -> 0 | H36: =H24-H34 -> 0 | I36: =I24-I34 -> 0 | J36: =J24-J34 -> 0 | ... N36: =N24-N34 -> 0 | O36: =SUM(C36:N36) -> 263.28
B37: Net margin % | C37: =IFERROR(C36/C12,0) -> -0.15683834 | D37: =IFERROR(D36/D12,0) -> -0.18662642 | E37: =IFERROR(E36/E12,0) -> -0.17351398 | F37: =IFERROR(F36/F12,0) -> 1 | G37: =IFERROR(G36/G12,0) -> 0 | H37: =IFERROR(H36/H12,0) -> 0 | I37: =IFERROR(I36/I12,0) -> 0 | J37: =IFERROR(J36/J12,0) -> 0 | ... N37: =IFERROR(N36/N12,0) -> 0 | O37: =IFERROR(AVERAGE(C37:N37),0) -> 0.040251772
B39: Corporation Tax reserve (19%) | C39: =MAX(0,C36)*0.19 -> 0 | D39: =MAX(0,D36)*0.19 -> 0 | E39: =MAX(0,E36)*0.19 -> 0 | F39: =MAX(0,F36)*0.19 -> 245.6795 | G39: =MAX(0,G36)*0.19 -> 0 | H39: =MAX(0,H36)*0.19 -> 0 | I39: =MAX(0,I36)*0.19 -> 0 | J39: =MAX(0,J36)*0.19 -> 0 | ... N39: =MAX(0,N36)*0.19 -> 0 | O39: =SUM(C39:N39) -> 245.6795
B40: NET PROFIT (after tax) | C40: =C36-C39 -> -283.49 | D40: =D36-D39 -> -323.39 | E40: =E36-E39 -> -422.89 | F40: =F36-F39 -> 1047.3705 | G40: =G36-G39 -> 0 | H40: =H36-H39 -> 0 | I40: =I36-I39 -> 0 | J40: =J36-J39 -> 0 | ... N40: =N36-N39 -> 0 | O40: =SUM(C40:N40) -> 17.6005

Sheet Yearly Summary
B2: Yearly Summary
B3: Year-to-date totals, split between card/cash, best and worst months, and key ratios.
B5: Year: | C5: ='Monthly P&L'!C5 -> 2026
B7: YTD totals
B8: Total revenue | D8: ='Monthly P&L'!O12 -> 7270.61
B9: Card sales | D9: ='Monthly P&L'!O9 -> 7200.99
B10: Square cash | D10: ='Monthly P&L'!O10 -> 69.62
B11: Own cash | D11: ='Monthly P&L'!O11 -> 0
B12: Total COGS | D12: ='Monthly P&L'!O22 -> 2738.22
B13: Gross profit | D13: ='Monthly P&L'!O24 -> 4532.39
B14: Gross margin % | D14: ='Monthly P&L'!O25 -> 0.21598172
B15: Total operating expenses | D15: ='Monthly P&L'!O34 -> 4269.11
B16: Net profit (before tax) | D16: ='Monthly P&L'!O36 -> 263.28
B17: Net margin % | D17: ='Monthly P&L'!O37 -> 0.040251772
B18: Net profit (after tax) | D18: ='Monthly P&L'!O40 -> 17.6005
B21: Payment mix
B22: Card as % of revenue | D22: =IFERROR('Monthly P&L'!O9/'Monthly P&L'!O12,0) -> 0.99042446
B23: Total cash as % of revenue | D23: =IFERROR(('Monthly P&L'!O10+'Monthly P&L'!O11)/'Monthly P&L'!O12,0) -> 0.0095755377
B24: Own-cash as % of total cash | D24: =IFERROR('Monthly P&L'!O11/('Monthly P&L'!O10+'Monthly P&L'!O11),0) -> 0
B26: Best & worst months (revenue)
B27: Best month (£) | D27: =MAX('Monthly P&L'!C12:N12) -> 2437.21
B28: Best month name | D28: =INDEX('Monthly P&L'!C7:N7,MATCH(MAX('Monthly P&L'!C12:N12),'Monthly P&L'!C12:N12,0)) -> Mar
B29: Worst month (£, excluding zero months) | D29: =IFERROR(MIN(IF('Monthly P&L'!C12:N12>0,'Monthly P&L'!C12:N12)),0) -> 0
B30: Trading months so far | D30: =COUNTIF('Monthly P&L'!C12:N12,">0") -> 4
B31: Average monthly revenue (active months) | D31: =IFERROR(AVERAGEIF('Monthly P&L'!C12:N12,">0"),0) -> 1817.6525
B33: Target progress
B34: Monthly revenue target (£) | D34: 5000
B35: Average month vs target | D35: =IFERROR(IFERROR(AVERAGEIF('Monthly P&L'!C12:N12,">0"),0)/D34,0) -> 0.3635305
B36: Annual target (12 × monthly) | D36: =D34*12 -> 60000
B37: YTD vs annual target | D37: =IFERROR('Monthly P&L'!O12/D36,0) -> 0.12117683

Sheet Dashboard
B2: Sasha's Corner — Dashboard
B3: Top view: this month + year to date. All numbers auto-update.
B5: Show month: | D5: 46113
B7: This month | G7: Year to date
B8: Revenue | D8: =INDEX('Monthly P&L'!C12:N12,MATCH(MONTH($D$5),{1,2,3,4,5,6,7,8,9,10,11,12},0)) -> 1293.05 | G8: YTD revenue | I8: ='Monthly P&L'!O12 -> 7270.61
B9: Card sales | D9: =INDEX('Monthly P&L'!C9:N9,MATCH(MONTH($D$5),{1,2,3,4,5,6,7,8,9,10,11,12},0)) -> 1293.05 | G9: YTD card | I9: ='Monthly P&L'!O9 -> 7200.99
B10: Total cash | D10: =INDEX('Monthly P&L'!C10:N10,MATCH(MONTH($D$5),{1,2,3,4,5,6,7,8,9,10,11,12},0))+INDEX('Monthly P&L'!C11:N11,MATCH(MONTH($D$5),{1,2,3,4,5,6,7,8,9,10,11,12},0)) -> 0 | G10: YTD cash (sq + own) | I10: ='Monthly P&L'!O10+'Monthly P&L'!O11 -> 69.62
B11: Gross profit | D11: =INDEX('Monthly P&L'!C24:N24,MATCH(MONTH($D$5),{1,2,3,4,5,6,7,8,9,10,11,12},0)) -> 1293.05 | G11: YTD gross profit | I11: ='Monthly P&L'!O24 -> 4532.39
B12: Net profit (before tax) | D12: =INDEX('Monthly P&L'!C36:N36,MATCH(MONTH($D$5),{1,2,3,4,5,6,7,8,9,10,11,12},0)) -> 1293.05 | G12: YTD net profit (before tax) | I12: ='Monthly P&L'!O36 -> 263.28
B13: Gross margin % | D13: =INDEX('Monthly P&L'!C25:N25,MATCH(MONTH($D$5),{1,2,3,4,5,6,7,8,9,10,11,12},0)) -> 1 | G13: YTD gross margin % | I13: ='Monthly P&L'!O25 -> 0.21598172
B14: Net margin % | D14: =INDEX('Monthly P&L'!C37:N37,MATCH(MONTH($D$5),{1,2,3,4,5,6,7,8,9,10,11,12},0)) -> 1 | G14: YTD net margin % | I14: ='Monthly P&L'!O37 -> 0.040251772
B17: Progress to target
B18: Monthly target (£) | D18: 5000
B19: This month actual | D19: =INDEX('Monthly P&L'!C12:N12,MATCH(MONTH($D$5),{1,2,3,4,5,6,7,8,9,10,11,12},0)) -> 1293.05
B20: % of target | D20: =IFERROR(D19/D18,0) -> 0.25861

Sheet Sources & Assumptions
B2: Sources, Assumptions & Open Questions
B3: Where the recipe estimates come from, what's been fixed, and what still needs your input.
B5: Size conventions used
B6: S / Small | C6: Hot: 8oz cup, 1 espresso shot, 160ml milk. Iced: 12oz cup, lighter liquid.
B7: M / Medium / Regular | C7: Hot: 12oz cup, 2 shots, 240ml milk. Iced: 16oz cup.
B8: XL / Large | C8: Hot: 16oz cup, 2 shots, 320ml milk. Iced: 16oz cup with more liquid.
B9: One (single size) | C9: Espressos, macchiatos, teas, flat whites, cortados — default 8oz cup, 1-2 shots as per drink.
B11: Standard recipe components
B12: Espresso shot | C12: 18g beans @ £22/kg | G12: £0.40
B13: Milk 160ml (S latte) | C13: 160ml whole @ £1.20/L | G13: £0.19
B14: Milk 240ml (M latte) | C14: 240ml whole @ £1.20/L | G14: £0.29
B15: Milk 320ml (XL latte) | C15: 320ml whole @ £1.20/L | G15: £0.38
B16: Monin syrup (M drink, 20ml) | C16: 20ml @ ~£0.008/ml | G16: £0.16
B17: Chocolate powder (M) | C17: 15g @ £9/kg | G17: £0.14
B18: White chocolate sauce (M) | C18: 30ml @ £10/L | G18: £0.30
B19: Matcha powder (M) | C19: 2g @ £80/kg | G19: £0.16
B20: Butterfly pea (blue matcha) | C20: 1g @ £40/kg | G20: £0.04
B21: Ice cream (M milkshake) | C21: 100ml @ £4/L | G21: £0.40
B22: Tapioca pearls (M bubble tea) | C22: 50g @ £8/kg (cooked) | G22: £0.40
B23: 12oz cup + lid + napkin | C23: £0.10 + £0.05 + £0.008 | G23: £0.16
B24: 16oz cup + lid + napkin | C24: £0.12 + £0.06 + £0.008 | G24: £0.19
B26: Typos fixed in this workbook (fix in Square too)
B27: Cappucino | C27: → Cappuccino
B28: cinammon classic | C28: → Cinnamon classic
B29: billionare's shortbread | C29: → Billionaire's shortbread
B30: rasperry and matcha cheescaks | C30: → Raspberry and matcha cheesecake
B31: strawberry blass | C31: → Strawberry bliss (likely intended)
B32: iced matcha plane | C32: → Iced matcha (plain)
B33: hot banana matcha M | C33: → Hot banana matcha (orphan 'M' dropped)
B34: Spring saesonal drinks (62 items) | C34: → Spring seasonal drinks
B35: Inconsistent capitalisation across menu | C35: → Title Case applied consistently
B36: Inconsistent size naming (S/M/XL vs Small/Regular/XL vs Small/Medium/XL) | C36: → Normalised to S/M/XL throughout this workbook. Pick one in Square.
B38: OPEN QUESTIONS — 12 items I still need clarity on
B39: Tropical Mint Bliss | C39: What's in it?
B40: Emerald Zest | C40: Composition?
B41: Strawberry (£3.90) | C41: Milkshake? Other?
B42: Strawberry bliss (was 'blass') | C42: What is it?
B43: Strawberry black | C43: Strawberry-flavoured black tea? Coffee?
B44: Black honey | C44: Tea-based? Other?
B45: 'card' (£3.00) | C45: Gift card / greeting card / card-payment fee?
B46: Juice (generic £1.90) | C46: Which juice?
B47: BKK Kyiv cake (£20) | C47: Different from Kyiv cake (whole)?
B48: Kyiv cake (whole, £25) | C48: Full cake? Size? Wholesale cost?
B49: Lunch deal (£6.95) / Afternoon deal (£5.00) | C49: Components?
B50: Homemade panini / Homemade roll | C50: Recipes?
B52: Data-hygiene observations on your Square catalogue
B53: Milk-variant SKU duplication | C53: Most multi-milk drinks have 2-4 SKUs per size. Fine for inventory, noisy for reporting. Audit at your convenience.
B54: Orphaned items | C54: 'hot banana matcha M' and 'hot blue matcha' exist as standalone items outside the normal size-variant structure. Likely accidental duplicates.
B55: Empty categories | C55: ~270 of 538 SKUs have no Reporting Category set in Square. Worth tagging when you edit — improves Square's own reports.
B56: Archive check | C56: Go through Square and archive anything you no longer sell — reduces catalogue noise.

Sheet Director Account
B2: Director's Account — Capital In & Drawings Out
B3: Tracks money YOU put in (capital injection) and money YOU take out (drawings). Not part of the operating P&L.
B5: Date | C5: Type | D5: Description | E5: Amount IN (£) | F5: Amount OUT (£) | G5: Notes
B6: 45908 | C6: Capital injection | D6: Initial Investment Dremliuha Y Bank transfer | E6: 3500 | G6: From your personal account
B7: 45965 | C7: Capital injection | D7: Initial Investment Dremliuha Y Bank transfer | E7: 2000 | G7: From your personal account
B8: 46001 | C8: Capital injection | D8: Full Time Job Dremliuha Y Bank transfer | E8: 450 | G8: From your personal account
B9: 46083 | C9: Capital injection | D9: Full Time Job Dremliuha Y Bank transfer | E9: 200 | G9: From your personal account
B10: 46111 | C10: Capital injection | D10: Full Time Job Sent Dremliuha Y Bank transfer | E10: 700 | G10: From your personal account
B11: 45951 | C11: Drawings | D11: Royal Bk Of Scotland Dundee Gbr Withdrawal | F11: 200 | G11: cash withdrawal
B12: 45984 | C12: Drawings | D12: Anduff Car Wash Limite Buckinghamshi Gbr Card purchase | F12: 13 | G12: Car wash — personal
B13: 45984 | C13: Drawings | D13: Forfar Road Service St Scotland Card purchase | F13: 82.89 | G13: Travel — likely personal
B14: 45984 | C14: Drawings | D14: Nya Scotia Forecourt S Dundee Card purchase | F14: 3 | G14: Personal
B15: 45985 | C15: Drawings | D15: Dundee Cc Parking Card purchase | F15: 4 | G15: Parking — personal
B16: 45985 | C16: Drawings | D16: Tenpin Dundee Card purchase | F16: 18.5 | G16: Personal expenditure on business card
B17: 45985 | C17: Drawings | D17: David Lloyds Leisure L Dundee Card purchase | F17: 3.46 | G17: Personal expenditure on business card
B18: 45986 | C18: Drawings | D18: Nya Tenpin Card purchase | F18: 1 | G18: Personal expenditure on business card
B19: 45986 | C19: Drawings | D19: Nya Tenpin Card purchase | F19: 2 | G19: Personal expenditure on business card
B20: 45986 | C20: Drawings | D20: Nya Tenpin Card purchase | F20: 1 | G20: Personal expenditure on business card
B21: 45987 | C21: Drawings | D21: The West House Card purchase | F21: 29.5 | G21: Restaurant — personal
B22: 45988 | C22: Drawings | D22: Pets At Home Card purchase | F22: 20.35 | G22: Personal expenditure on business card
... B54: 46112 | C54: Drawings | D54: Ncp.co.uk Card purchase | F54: 4.95 | G54: Parking — likely personal
D56: TOTAL: | E56: =SUM(E6:E54) -> 6850 | F56: =SUM(F6:F54) -> 563.54
C58: Director's account balance: | E58: =E56-F56 -> 6286.46
C59: (Positive = company owes you. Negative = you owe company.)
